{
  "type": "Feature",
  "properties": {
    "gn:admin1_code":"14",
    "gn:admin2_code":"01",
    "gn:asciiname":"Horqueta",
    "gn:cc2":"UY",
    "gn:country_code":"UY",
    "gn:dem":90,
    "gn:feature_class":"P",
    "gn:feature_code":"PPL",
    "gn:name":"Horqueta",
    "gn:population":0,
    "gn:timezone":"America/Montevideo",
    "iso:country":"UY",
    "name:deu_x_preferred":[
        "Horqueta"
    ],
    "name:eus_x_preferred":[
        "Horqueta"
    ],
    "name:grn_x_preferred":[
        "Ork\u00e9ta"
    ],
    "name:ita_x_preferred":[
        "Horqueta"
    ],
    "name:kat_x_preferred":[
        "\u10dd\u10e0\u10d9\u10d4\u10e2\u10d0"
    ],
    "name:lit_x_preferred":[
        "Horketa"
    ],
    "name:nld_x_preferred":[
        "Horqueta"
    ],
    "name:pol_x_preferred":[
        "Horqueta"
    ],
    "name:por_x_preferred":[
        "Horqueta"
    ],
    "name:spa_x_preferred":[
        "Horqueta"
    ],
    "name:und_x_variant":[
        "Horqueta de Castillos"
    ],
    "name:zho_x_preferred":[
        "\u5967\u723e\u514b\u5854"
    ],
    "wof:name":"Horqueta",
    "wof:placetype":"locality"
},
  "geometry": {"coordinates":[-53.95,-34.11667],"type":"Point"}
}