{
  "type": "Feature",
  "properties": {
    "gn:admin1_code":"14",
    "gn:admin2_code":"01",
    "gn:asciiname":"Horqueta",
    "gn:cc2":"UY",
    "gn:country_code":"UY",
    "gn:dem":90,
    "gn:feature_class":"P",
    "gn:feature_code":"PPL",
    "gn:name":"Horqueta",
    "gn:population":0,
    "gn:timezone":"America/Montevideo",
    "iso:country":"UY",
    "name:und_x_variant":[
        "Horqueta de Castillos",
        "Horqueta"
    ],
    "wof:name":"Horqueta",
    "wof:placetype":"locality"
},
  "geometry": {"coordinates":[-53.95,-34.11667],"type":"Point"}
}