{
  "type": "Feature",
  "properties": {
    "gn:admin1_code":"02",
    "gn:admin2_code":"06",
    "gn:asciiname":"Parada Cabrera",
    "gn:country_code":"UY",
    "gn:dem":40,
    "gn:feature_class":"P",
    "gn:feature_code":"PPL",
    "gn:name":"Parada Cabrera",
    "gn:population":0,
    "gn:timezone":"America/Montevideo",
    "iso:country":"UY",
    "name:spa_x_preferred":[
        "Parada Cabrera"
    ],
    "wof:name":"Parada Cabrera",
    "wof:placetype":"locality"
},
  "geometry": {"coordinates":[-56.2545,-34.62384],"type":"Point"}
}