{
  "type": "Feature",
  "properties": {
    "gn:admin1_code":"19",
    "gn:asciiname":"Villa Passano",
    "gn:country_code":"UY",
    "gn:dem":12,
    "gn:feature_class":"P",
    "gn:feature_code":"PPL",
    "gn:name":"Villa Passano",
    "gn:population":0,
    "gn:timezone":"America/Montevideo",
    "iso:country":"UY",
    "name:und_x_variant":[
        "Picada de Passano",
        "Villa Passano"
    ],
    "wof:name":"Villa Passano",
    "wof:placetype":"locality"
},
  "geometry": {"coordinates":[-53.90075,-33.29073],"type":"Point"}
}