{
  "type": "Feature",
  "properties": {
    "gn:admin1_code":"04",
    "gn:admin2_code":"01",
    "gn:asciiname":"Zagarzazu",
    "gn:country_code":"UY",
    "gn:dem":16,
    "gn:feature_class":"P",
    "gn:feature_code":"PPL",
    "gn:name":"Zagarzaz\u00fa",
    "gn:population":0,
    "gn:timezone":"America/Montevideo",
    "iso:country":"UY",
    "name:spa_x_preferred":[
        "Zagarzaz\u00fa"
    ],
    "wof:name":"Zagarzazu",
    "wof:placetype":"locality"
},
  "geometry": {"coordinates":[-58.33093,-33.96354],"type":"Point"}
}