{
  "type": "Feature",
  "properties": {
    "gn:admin1_code":"06",
    "gn:asciiname":"Juan Jose Castro",
    "gn:cc2":"UY",
    "gn:country_code":"UY",
    "gn:dem":130,
    "gn:feature_class":"P",
    "gn:feature_code":"PPL",
    "gn:name":"Juan Jos\u00e9 Castro",
    "gn:population":0,
    "gn:timezone":"America/Montevideo",
    "iso:country":"UY",
    "name:und_x_variant":[
        "Juan J. Castro",
        "Juan Jos\u00e9 Castro"
    ],
    "wof:name":"Juan Jose Castro",
    "wof:placetype":"locality"
},
  "geometry": {"coordinates":[-56.74411,-33.49397],"type":"Point"}
}