{
  "type": "Feature",
  "properties": {
    "gn:admin1_code":"15",
    "gn:admin2_code":"04",
    "gn:asciiname":"Musi",
    "gn:country_code":"UY",
    "gn:dem":129,
    "gn:feature_class":"P",
    "gn:feature_code":"PPL",
    "gn:name":"Musi",
    "gn:population":0,
    "gn:timezone":"America/Montevideo",
    "iso:country":"UY",
    "wof:name":"Musi",
    "wof:placetype":"locality"
},
  "geometry": {"coordinates":[-56.51667,-31.08333],"type":"Point"}
}