{
  "type": "Feature",
  "properties": {
    "gn:admin1_code":"04",
    "gn:asciiname":"Fomento",
    "gn:country_code":"UY",
    "gn:dem":23,
    "gn:feature_class":"P",
    "gn:feature_code":"PPL",
    "gn:name":"Fomento",
    "gn:population":0,
    "gn:timezone":"America/Montevideo",
    "iso:country":"UY",
    "name:fra_x_preferred":[
        "Fomento"
    ],
    "name:hat_x_preferred":[
        "Fomento"
    ],
    "name:ita_x_preferred":[
        "Fomento"
    ],
    "name:kat_x_preferred":[
        "\u10e4\u10dd\u10db\u10d4\u10dc\u10e2\u10dd"
    ],
    "name:por_x_preferred":[
        "Fomento"
    ],
    "name:sco_x_preferred":[
        "Fomento"
    ],
    "name:spa_x_preferred":[
        "Fomento"
    ],
    "name:vie_x_preferred":[
        "Fomento"
    ],
    "name:zho_x_preferred":[
        "\u798f\u9580\u6258"
    ],
    "wof:name":"Fomento",
    "wof:placetype":"locality"
},
  "geometry": {"coordinates":[-57.2537,-34.43323],"type":"Point"}
}