{
  "type": "Feature",
  "properties": {
    "gn:admin1_code":"07",
    "gn:asciiname":"Berrondo",
    "gn:country_code":"UY",
    "gn:dem":75,
    "gn:feature_class":"P",
    "gn:feature_code":"PPL",
    "gn:name":"Berrondo",
    "gn:population":0,
    "gn:timezone":"America/Montevideo",
    "iso:country":"UY",
    "name:spa_x_preferred":[
        "Berrondo"
    ],
    "wof:name":"Berrondo",
    "wof:placetype":"locality"
},
  "geometry": {"coordinates":[-56.27753000000001,-34.14737],"type":"Point"}
}