{
  "type": "Feature",
  "properties": {
    "gn:admin1_code":"07",
    "gn:asciiname":"Chilcas",
    "gn:country_code":"UY",
    "gn:dem":127,
    "gn:feature_class":"P",
    "gn:feature_code":"PPL",
    "gn:name":"Chilcas",
    "gn:population":0,
    "gn:timezone":"America/Montevideo",
    "iso:country":"UY",
    "name:por_x_preferred":[
        "Chilcas"
    ],
    "name:spa_x_preferred":[
        "Chilcas"
    ],
    "wof:name":"Chilcas",
    "wof:placetype":"locality"
},
  "geometry": {"coordinates":[-55.66667,-33.55],"type":"Point"}
}