{
  "type": "Feature",
  "properties": {
    "gn:country":"UY",
    "gn:fcode":"PPL",
    "gn:pop":24047,
    "iso:country":"UY",
    "name:ara_x_preferred":[
        "\u0628\u0627\u0646\u062f\u0648\u060c \u0623\u0648\u0631\u0648\u063a\u0648\u0627\u064a"
    ],
    "name:arm_x_preferred":[
        "\u054a\u0561\u0576\u0564\u0578"
    ],
    "name:bel_x_preferred":[
        "\u041f\u0430\u043d\u0434\u0430"
    ],
    "name:ben_x_preferred":[
        "\u09aa\u09be\u09a8\u09cd\u09a1\u09cb"
    ],
    "name:cat_x_preferred":[
        "Pando"
    ],
    "name:chi_x_preferred":[
        "\u6f58\u591a"
    ],
    "name:dan_x_preferred":[
        "Pando"
    ],
    "name:dut_x_preferred":[
        "Pando"
    ],
    "name:eng_x_preferred":[
        "Pando"
    ],
    "name:fin_x_preferred":[
        "Pando"
    ],
    "name:fre_x_preferred":[
        "Pando"
    ],
    "name:geo_x_preferred":[
        "\u10de\u10d0\u10dc\u10d3\u10dd"
    ],
    "name:ger_x_preferred":[
        "Pando"
    ],
    "name:gre_x_preferred":[
        "\u03a0\u03ac\u03bd\u03c4\u03bf"
    ],
    "name:guj_x_preferred":[
        "\u0aaa\u0abe\u0a82\u0aa1\u0acb"
    ],
    "name:heb_x_preferred":[
        "\u05e4\u05e0\u05d3\u05d5"
    ],
    "name:hin_x_preferred":[
        "\u092a\u093e\u0902\u0921\u094b"
    ],
    "name:ind_x_preferred":[
        "Pando"
    ],
    "name:ita_x_preferred":[
        "Pando"
    ],
    "name:jpn_x_preferred":[
        "\u30d1\u30f3\u30c9"
    ],
    "name:kan_x_preferred":[
        "\u0caa\u0cbe\u0c82\u0ca1\u0cca"
    ],
    "name:kor_x_preferred":[
        "\ud310\ub3c4"
    ],
    "name:lav_x_preferred":[
        "Pando"
    ],
    "name:lit_x_preferred":[
        "Pandas"
    ],
    "name:mar_x_preferred":[
        "\u092a\u093e\u0902\u0921\u094b"
    ],
    "name:may_x_preferred":[
        "Pando"
    ],
    "name:nob_x_preferred":[
        "Pando"
    ],
    "name:per_x_preferred":[
        "\u067e\u0646\u062f\u0648\u060c \u0627\u0631\u0648\u06af\u0648\u0626\u0647"
    ],
    "name:pol_x_preferred":[
        "Pando"
    ],
    "name:por_x_preferred":[
        "Pando"
    ],
    "name:rus_x_preferred":[
        "\u041f\u0430\u043d\u0434\u043e"
    ],
    "name:sin_x_preferred":[
        "\u0db4\u0dd0\u0db1\u0dca\u0da9\u0ddd"
    ],
    "name:spa_x_preferred":[
        "Pando"
    ],
    "name:swe_x_preferred":[
        "Pando"
    ],
    "name:tam_x_preferred":[
        "\u0baa\u0ba3\u0bcd\u0b9f\u0bcb"
    ],
    "name:tel_x_preferred":[
        "\u0c2a\u0c3e\u0c02\u0c21\u0c4b"
    ],
    "name:tha_x_preferred":[
        "\u0e41\u0e1e\u0e19\u0e42\u0e14"
    ],
    "name:tur_x_preferred":[
        "Pando"
    ],
    "name:ukr_x_preferred":[
        "\u041f\u0430\u043d\u0434\u043e"
    ],
    "name:unk_x_variant":[
        "Villa de Pando"
    ],
    "name:urd_x_preferred":[
        "\u067e\u0627\u0646\u062f\u0648\u060c \u06cc\u0648\u0631\u0627\u06af\u0648\u0626\u06d2"
    ],
    "name:vie_x_preferred":[
        "Pando"
    ],
    "qs:name":"Pando",
    "qs:photos_9r":0,
    "qs:photos_sr":0,
    "qs:pop_sr":"7",
    "wd:wordcount":162,
    "wof:name":"Pando",
    "wof:placetype":"locality",
    "wof:population":24047
},
  "geometry": {"coordinates":[-55.95,-34.71667],"type":"Point"}
}