{
  "type": "Feature",
  "properties": {
    "gn:admin1_code":"08",
    "gn:asciiname":"Molles de Canada Grande",
    "gn:country_code":"UY",
    "gn:dem":53,
    "gn:feature_class":"P",
    "gn:feature_code":"PPL",
    "gn:name":"Molles de Ca\u00f1ada Grande",
    "gn:population":0,
    "gn:timezone":"America/Montevideo",
    "iso:country":"UY",
    "name:spa_x_preferred":[
        "Molles de Ca\u00f1ada Grande"
    ],
    "wof:name":"Molles de Canada Grande",
    "wof:placetype":"locality"
},
  "geometry": {"coordinates":[-54.54265,-33.6221],"type":"Point"}
}