{
  "type": "Feature",
  "properties": {
    "gn:country":"UY",
    "gn:fcode":"PPL",
    "gn:pop":9335,
    "iso:country":"UY",
    "name:cat_x_preferred":[
        "Nueva Palmira"
    ],
    "name:chi_x_preferred":[
        "\u65b0\u5e15\u723e\u7c73\u62c9"
    ],
    "name:dut_x_preferred":[
        "Nueva Palmira"
    ],
    "name:eng_x_preferred":[
        "Nueva Palmira"
    ],
    "name:fas_x_preferred":[
        "\u0646\u0648\u0626\u0648\u0627 \u067e\u0627\u0644\u0645\u06cc\u0631\u0627"
    ],
    "name:fre_x_preferred":[
        "Nueva Palmira"
    ],
    "name:ger_x_preferred":[
        "Nueva Palmira"
    ],
    "name:heb_x_preferred":[
        "\u05e0\u05d5\u05d0\u05d1\u05d4 \u05e4\u05dc\u05de\u05d9\u05e8\u05d4"
    ],
    "name:hrv_x_preferred":[
        "Nueva Palmira"
    ],
    "name:ita_x_preferred":[
        "Nueva Palmira"
    ],
    "name:jpn_x_preferred":[
        "\u30cc\u30a8\u30d0\u30fb\u30d1\u30eb\u30df\u30e9"
    ],
    "name:nob_x_preferred":[
        "Nueva Palmira"
    ],
    "name:per_x_preferred":[
        "\u0646\u0648\u0626\u0648\u0627 \u067e\u0627\u0644\u0645\u06cc\u0631\u0627"
    ],
    "name:pol_x_preferred":[
        "Nueva Palmira"
    ],
    "name:por_x_preferred":[
        "Nueva Palmira"
    ],
    "name:rus_x_preferred":[
        "\u041d\u0443\u044d\u0432\u0430-\u041f\u0430\u043b\u044c\u043c\u0438\u0440\u0430"
    ],
    "name:spa_x_preferred":[
        "Nueva Palmira"
    ],
    "name:urd_x_preferred":[
        "\u0646\u0648\u06cc\u0648\u0627 \u067e\u0627\u0644\u0645\u06cc\u0631\u0627"
    ],
    "name:zho_x_preferred":[
        "\u65b0\u5e15\u723e\u7c73\u62c9"
    ],
    "qs:name":"Nueva Palmira",
    "qs:photos_9r":0,
    "qs:photos_sr":0,
    "qs:pop_sr":"5",
    "wd:wordcount":398,
    "wof:name":"Nueva Palmira",
    "wof:placetype":"locality",
    "wof:population":9335
},
  "geometry": {"coordinates":[-58.41667,-33.88333],"type":"Point"}
}