{
  "type": "Feature",
  "properties": {
    "gn:admin1_code":"15",
    "gn:admin2_code":"06",
    "gn:asciiname":"Puntas de Valentin",
    "gn:country_code":"UY",
    "gn:dem":126,
    "gn:feature_class":"P",
    "gn:feature_code":"PPL",
    "gn:name":"Puntas de Valent\u00edn",
    "gn:population":0,
    "gn:timezone":"America/Montevideo",
    "iso:country":"UY",
    "name:spa_x_preferred":[
        "Puntas de Valent\u00edn"
    ],
    "wof:name":"Puntas de Valentin",
    "wof:placetype":"locality"
},
  "geometry": {"coordinates":[-57.13294000000001,-31.49686],"type":"Point"}
}