{
  "type": "Feature",
  "properties": {
    "gn:admin1_code":"18",
    "gn:asciiname":"Poblado los Silveira",
    "gn:cc2":"UY",
    "gn:country_code":"UY",
    "gn:dem":116,
    "gn:feature_class":"P",
    "gn:feature_code":"PPL",
    "gn:name":"Poblado los Silveira",
    "gn:population":0,
    "gn:timezone":"America/Montevideo",
    "iso:country":"UY",
    "name:und_x_variant":[
        "Los Silveyra",
        "Poblado los Silveira"
    ],
    "wof:name":"Poblado los Silveira",
    "wof:placetype":"locality"
},
  "geometry": {"coordinates":[-54.91667,-32.26667],"type":"Point"}
}