{
  "type": "Feature",
  "properties": {
    "gn:admin1_code":"04",
    "gn:asciiname":"Radial Conchillas",
    "gn:country_code":"UY",
    "gn:dem":69,
    "gn:feature_class":"P",
    "gn:feature_code":"PPL",
    "gn:name":"Radial Conchillas",
    "gn:population":0,
    "gn:timezone":"America/Montevideo",
    "iso:country":"UY",
    "name:spa_x_preferred":[
        "Radial Conchillas"
    ],
    "wof:name":"Radial Conchillas",
    "wof:placetype":"locality"
},
  "geometry": {"coordinates":[-58.00787,-34.12133],"type":"Point"}
}