{
  "type": "Feature",
  "properties": {
    "gn:admin1_code":"14",
    "gn:asciiname":"El Ceibo",
    "gn:country_code":"UY",
    "gn:dem":9,
    "gn:feature_class":"P",
    "gn:feature_code":"PPL",
    "gn:name":"El Ceibo",
    "gn:population":0,
    "gn:timezone":"America/Montevideo",
    "iso:country":"UY",
    "wof:name":"El Ceibo",
    "wof:placetype":"locality"
},
  "geometry": {"coordinates":[-53.78333000000001,-33.51667],"type":"Point"}
}