{
  "type": "Feature",
  "properties": {
    "gn:admin1_code":"10",
    "gn:admin2_code":"01",
    "gn:asciiname":"Villa del Cerro",
    "gn:country_code":"UY",
    "gn:dem":29,
    "gn:feature_class":"P",
    "gn:feature_code":"PPL",
    "gn:name":"Villa del Cerro",
    "gn:population":0,
    "gn:timezone":"America/Montevideo",
    "iso:country":"UY",
    "name:lit_x_preferred":[
        "Vilja del Seras"
    ],
    "wof:name":"Villa del Cerro",
    "wof:placetype":"locality"
},
  "geometry": {"coordinates":[-56.25292,-34.89441],"type":"Point"}
}