{
  "type": "Feature",
  "properties": {
    "gn:admin1_code":"06",
    "gn:asciiname":"Los Ahogados",
    "gn:country_code":"UY",
    "gn:dem":106,
    "gn:feature_class":"P",
    "gn:feature_code":"PPL",
    "gn:name":"Los Ahogados",
    "gn:population":0,
    "gn:timezone":"America/Montevideo",
    "iso:country":"UY",
    "wof:name":"Los Ahogados",
    "wof:placetype":"locality"
},
  "geometry": {"coordinates":[-56.93333000000001,-33.53333],"type":"Point"}
}