{
  "type": "Feature",
  "properties": {
    "gn:admin1_code":"01",
    "gn:asciiname":"Bernabe Rivera",
    "gn:country_code":"UY",
    "gn:dem":77,
    "gn:feature_class":"P",
    "gn:feature_code":"PPL",
    "gn:name":"Bernab\u00e9 Rivera",
    "gn:population":0,
    "gn:timezone":"America/Montevideo",
    "iso:country":"UY",
    "name:und_x_variant":[
        "Bernab\u00e9 Rivera"
    ],
    "wof:name":"Bernabe Rivera",
    "wof:placetype":"locality"
},
  "geometry": {"coordinates":[-56.97047,-30.2983],"type":"Point"}
}