{
  "type": "Feature",
  "properties": {
    "iso:country":"UY",
    "name:bul_x_preferred":[
        "\u041c\u0438\u0433\u0443\u0435\u0441"
    ],
    "name:cat_x_preferred":[
        "Migues"
    ],
    "name:deu_x_preferred":[
        "Migues"
    ],
    "name:eng_x_preferred":[
        "Migues"
    ],
    "name:fra_x_preferred":[
        "Migues"
    ],
    "name:ita_x_preferred":[
        "Migues"
    ],
    "name:nld_x_preferred":[
        "Migues"
    ],
    "name:nob_x_preferred":[
        "Migues"
    ],
    "name:nor_x_preferred":[
        "Migues"
    ],
    "name:oci_x_preferred":[
        "Migues"
    ],
    "name:rus_x_preferred":[
        "\u041c\u0438\u0433\u0435\u0441"
    ],
    "name:spa_x_preferred":[
        "Migues"
    ],
    "name:unk_x_variant":[
        "Miguez"
    ],
    "name:urd_x_preferred":[
        "\u0645\u06cc\u063a\u06cc\u0633"
    ],
    "name:zho_x_preferred":[
        "\u7c73\u683c\u65af"
    ],
    "qs:gn_country":"UY",
    "qs:gn_fcode":"PPL",
    "qs:gn_pop":2203,
    "qs:name":"Migues",
    "qs:name_adm0":"Uruguay",
    "qs:name_adm1":"Canelones",
    "qs:photos":0,
    "qs:photos_1k":0,
    "qs:photos_9k":0,
    "qs:photos_9r":0,
    "qs:photos_all":0,
    "qs:photos_sr":0,
    "qs:placetype":"Town",
    "qs:pop_sr":"4",
    "qs:woe_adm0":23424979,
    "wd:wordcount":241,
    "wof:name":"Migues",
    "wof:placetype":"locality",
    "wof:population":2203
},
  "geometry": {"coordinates":[-55.65,-34.48333],"type":"Point"}
}