{
  "type": "Feature",
  "properties": {
    "iso:country":"UY",
    "name:cat_x_preferred":[
        "Quebracho"
    ],
    "name:ceb_x_preferred":[
        "Quebracho"
    ],
    "name:deu_x_preferred":[
        "Quebracho"
    ],
    "name:eng_x_preferred":[
        "Quebracho"
    ],
    "name:fra_x_preferred":[
        "Quebracho"
    ],
    "name:ita_x_preferred":[
        "Quebracho"
    ],
    "name:nld_x_preferred":[
        "Quebracho"
    ],
    "name:nob_x_preferred":[
        "Quebracho"
    ],
    "name:nor_x_preferred":[
        "Quebracho"
    ],
    "name:rus_x_preferred":[
        "\u041a\u0435\u0431\u0440\u0430\u0447\u043e"
    ],
    "name:spa_x_preferred":[
        "Quebracho"
    ],
    "name:zho_x_preferred":[
        "\u514b\u5e03\u62c9\u55ac"
    ],
    "qs:gn_country":"UY",
    "qs:gn_fcode":"PPL",
    "qs:gn_pop":2871,
    "qs:name":"Quebracho",
    "qs:name_adm0":"Uruguay",
    "qs:name_adm1":"Paysand\u00fa",
    "qs:photos":0,
    "qs:photos_1k":0,
    "qs:photos_9k":1,
    "qs:photos_9r":3,
    "qs:photos_all":84,
    "qs:photos_sr":0,
    "qs:placetype":"Town",
    "qs:pop_sr":"4",
    "qs:woe_adm0":23424979,
    "wd:wordcount":187,
    "wof:name":"Quebracho",
    "wof:placetype":"locality",
    "wof:population":2871
},
  "geometry": {"coordinates":[-57.88333,-31.95],"type":"Point"}
}