{
  "type": "Feature",
  "properties": {
    "gn:admin1_code":"08",
    "gn:asciiname":"Rincon de Mariscala",
    "gn:country_code":"UY",
    "gn:dem":69,
    "gn:feature_class":"P",
    "gn:feature_code":"PPL",
    "gn:name":"Rinc\u00f3n de Mariscala",
    "gn:population":0,
    "gn:timezone":"America/Montevideo",
    "iso:country":"UY",
    "name:spa_x_preferred":[
        "Rinc\u00f3n de Mariscala"
    ],
    "wof:name":"Rincon de Mariscala",
    "wof:placetype":"locality"
},
  "geometry": {"coordinates":[-54.58557,-33.93474000000001],"type":"Point"}
}