{
  "type": "Feature",
  "properties": {
    "gn:admin1_code":"17",
    "gn:asciiname":"Colonia Diaz",
    "gn:country_code":"UY",
    "gn:dem":38,
    "gn:feature_class":"P",
    "gn:feature_code":"PPL",
    "gn:name":"Colonia D\u00edaz",
    "gn:population":0,
    "gn:timezone":"America/Montevideo",
    "iso:country":"UY",
    "name:spa_x_preferred":[
        "Colonia D\u00edaz"
    ],
    "wof:name":"Colonia Diaz",
    "wof:placetype":"locality"
},
  "geometry": {"coordinates":[-58.03778000000001,-33.32708],"type":"Point"}
}