{
  "type": "Feature",
  "properties": {
    "gn:admin1_code":"19",
    "gn:asciiname":"Anastasia",
    "gn:country_code":"UY",
    "gn:dem":54,
    "gn:feature_class":"P",
    "gn:feature_code":"PPL",
    "gn:name":"Anastasia",
    "gn:population":0,
    "gn:timezone":"America/Montevideo",
    "iso:country":"UY",
    "wof:name":"Anastasia",
    "wof:placetype":"locality"
},
  "geometry": {"coordinates":[-54.38333000000001,-33.21667],"type":"Point"}
}