{
  "type": "Feature",
  "properties": {
    "gn:admin1_code":"19",
    "gn:asciiname":"Anastasia",
    "gn:country_code":"UY",
    "gn:dem":54,
    "gn:feature_class":"P",
    "gn:feature_code":"PPL",
    "gn:name":"Anastasia",
    "gn:population":0,
    "gn:timezone":"America/Montevideo",
    "iso:country":"UY",
    "name:dan_x_preferred":[
        "Anastasia"
    ],
    "name:deu_x_preferred":[
        "Anastasia"
    ],
    "name:ell_x_preferred":[
        "\u0391\u03bd\u03b1\u03c3\u03c4\u03b1\u03c3\u03af\u03b1"
    ],
    "name:epo_x_preferred":[
        "Anastazio"
    ],
    "name:fin_x_preferred":[
        "Anastasia"
    ],
    "name:fra_x_preferred":[
        "Anastasia"
    ],
    "name:heb_x_preferred":[
        "\u05d0\u05e0\u05e1\u05d8\u05e1\u05d9\u05d4"
    ],
    "name:isl_x_preferred":[
        "Anastas\u00eda"
    ],
    "name:ita_x_preferred":[
        "Anastasia"
    ],
    "name:kor_x_preferred":[
        "\uc544\ub098\uc2a4\ud0c0\uc2dc\uc544"
    ],
    "name:nor_x_preferred":[
        "Anastasia"
    ],
    "name:pol_x_preferred":[
        "Anastazja"
    ],
    "name:ron_x_preferred":[
        "Anastasia"
    ],
    "name:slv_x_preferred":[
        "Anastazija"
    ],
    "name:spa_x_preferred":[
        "Anastasia"
    ],
    "name:swe_x_preferred":[
        "Anastasia"
    ],
    "name:tgl_x_preferred":[
        "Anastasia"
    ],
    "wof:name":"Anastasia",
    "wof:placetype":"locality"
},
  "geometry": {"coordinates":[-54.38333000000001,-33.21667],"type":"Point"}
}