{
  "type": "Feature",
  "properties": {
    "gn:gn_country":"UY",
    "iso:country":"UY",
    "name:ceb_x_preferred":[
        "Las Delicias"
    ],
    "name:ita_x_preferred":[
        "Las Delicias"
    ],
    "name:swe_x_preferred":[
        "Las Delicias"
    ],
    "qs_pg:aaroncc":"UY",
    "qs_pg:gn_country":"UY",
    "qs_pg:name":"Las Delicias",
    "qs_pg:name_adm0":"Uruguay",
    "qs_pg:name_adm1":"Maldonado",
    "qs_pg:photos":412,
    "qs_pg:photos_1k":83,
    "qs_pg:photos_9k":2,
    "qs_pg:photos_9r":5,
    "qs_pg:photos_all":412,
    "qs_pg:photos_sr":6,
    "qs_pg:pop_sr":0,
    "qs_pg:qs_pg_placetype":"locality",
    "qs_pg:qs_pg_placetype_gp":"Town",
    "qs_pg:woe_adm0":23424979,
    "woe:adm0_id":23424979,
    "woe:name_adm0":"Uruguay",
    "woe:name_adm1":"Maldonado",
    "woe:placetype":"Town",
    "wof:name":"Las Delicias",
    "wof:placetype":"locality"
},
  "geometry": {"coordinates":[-54.971551,-34.925395],"type":"Point"}
}