{
  "type": "Feature",
  "properties": {
    "gn:admin1_code":"17",
    "gn:asciiname":"Cuchilla del Perdido",
    "gn:country_code":"UY",
    "gn:dem":150,
    "gn:feature_class":"P",
    "gn:feature_code":"PPL",
    "gn:name":"Cuchilla del Perdido",
    "gn:population":0,
    "gn:timezone":"America/Montevideo",
    "iso:country":"UY",
    "name:spa_x_preferred":[
        "Cuchilla del Perdido"
    ],
    "wof:name":"Cuchilla del Perdido",
    "wof:placetype":"locality"
},
  "geometry": {"coordinates":[-57.26488000000001,-33.72084],"type":"Point"}
}