{
  "type": "Feature",
  "properties": {
    "gn:admin1_code":"18",
    "gn:asciiname":"Las Toscas",
    "gn:cc2":"UY",
    "gn:country_code":"UY",
    "gn:dem":112,
    "gn:feature_class":"P",
    "gn:feature_code":"PPL",
    "gn:name":"Las Toscas",
    "gn:population":0,
    "gn:timezone":"America/Montevideo",
    "iso:country":"UY",
    "name:und_x_variant":[
        "Paso de las Toscas",
        "Las Toscas"
    ],
    "wof:name":"Las Toscas",
    "wof:placetype":"locality"
},
  "geometry": {"coordinates":[-55.0143,-32.17663],"type":"Point"}
}