{
  "type": "Feature",
  "properties": {
    "gn:admin1_code":"18",
    "gn:asciiname":"Las Toscas",
    "gn:cc2":"UY",
    "gn:country_code":"UY",
    "gn:dem":112,
    "gn:feature_class":"P",
    "gn:feature_code":"PPL",
    "gn:name":"Las Toscas",
    "gn:population":0,
    "gn:timezone":"America/Montevideo",
    "iso:country":"UY",
    "name:cat_x_preferred":[
        "Las Toscas"
    ],
    "name:deu_x_preferred":[
        "Las Toscas"
    ],
    "name:fra_x_preferred":[
        "Las Toscas"
    ],
    "name:hye_x_preferred":[
        "\u053c\u0561\u057d \u054f\u0578\u057d\u056f\u0561\u057d"
    ],
    "name:nor_x_preferred":[
        "Las Toscas"
    ],
    "name:rus_x_preferred":[
        "\u041b\u0430\u0441-\u0422\u043e\u0441\u043a\u0430\u0441"
    ],
    "name:spa_x_preferred":[
        "Las Toscas"
    ],
    "name:und_x_variant":[
        "Paso de las Toscas",
        "Las Toscas"
    ],
    "name:urd_x_preferred":[
        "\u0644\u0627\u0633 \u0679\u0648\u0633\u06a9\u0627\u0633"
    ],
    "wof:name":"Las Toscas",
    "wof:placetype":"locality"
},
  "geometry": {"coordinates":[-55.0143,-32.17663],"type":"Point"}
}