{
  "type": "Feature",
  "properties": {
    "gn:admin1_code":"13",
    "gn:asciiname":"Moirones",
    "gn:cc2":"UY",
    "gn:country_code":"UY",
    "gn:dem":189,
    "gn:feature_class":"P",
    "gn:feature_code":"PPL",
    "gn:name":"Moirones",
    "gn:population":0,
    "gn:timezone":"America/Montevideo",
    "iso:country":"UY",
    "name:und_x_variant":[
        "Poblado Moirones",
        "Moirones"
    ],
    "wof:name":"Moirones",
    "wof:placetype":"locality"
},
  "geometry": {"coordinates":[-54.98546999999999,-31.60427],"type":"Point"}
}