{
  "type": "Feature",
  "properties": {
    "gn:admin1_code":"04",
    "gn:asciiname":"Los Cerros de San Juan",
    "gn:country_code":"UY",
    "gn:dem":45,
    "gn:feature_class":"P",
    "gn:feature_code":"PPL",
    "gn:name":"Los Cerros de San Juan",
    "gn:population":0,
    "gn:timezone":"America/Montevideo",
    "iso:country":"UY",
    "wof:name":"Los Cerros de San Juan",
    "wof:placetype":"locality"
},
  "geometry": {"coordinates":[-57.93073,-34.21870999999999],"type":"Point"}
}