{
  "type": "Feature",
  "properties": {
    "gn:gn_country":"UY",
    "iso:country":"UY",
    "qs_pg:aaroncc":"UY",
    "qs_pg:gn_country":"UY",
    "qs_pg:name":"Arachania",
    "qs_pg:name_adm0":"Uruguay",
    "qs_pg:name_adm1":"Rocha",
    "qs_pg:photos":110,
    "qs_pg:photos_1k":22,
    "qs_pg:photos_9k":1,
    "qs_pg:photos_9r":3,
    "qs_pg:photos_all":110,
    "qs_pg:photos_sr":3,
    "qs_pg:pop_sr":0,
    "qs_pg:qs_pg_placetype":"locality",
    "qs_pg:qs_pg_placetype_gp":"Town",
    "qs_pg:woe_adm0":23424979,
    "woe:adm0_id":23424979,
    "woe:name_adm0":"Uruguay",
    "woe:name_adm1":"Rocha",
    "woe:placetype":"Town",
    "wof:name":"Arachania",
    "wof:placetype":"locality"
},
  "geometry": {"coordinates":[-54.105091,-34.576125],"type":"Point"}
}