{
  "type": "Feature",
  "properties": {
    "gn:admin1_code":"15",
    "gn:admin2_code":"06",
    "gn:asciiname":"Rincon de Valentin",
    "gn:country_code":"UY",
    "gn:dem":76,
    "gn:feature_class":"P",
    "gn:feature_code":"PPL",
    "gn:name":"Rinc\u00f3n de Valent\u00edn",
    "gn:population":0,
    "gn:timezone":"America/Montevideo",
    "iso:country":"UY",
    "name:spa_x_preferred":[
        "Rinc\u00f3n de Valent\u00edn"
    ],
    "name:und_x_variant":[
        "Rinc\u00f3n de Valentines"
    ],
    "wof:name":"Rincon de Valentin",
    "wof:placetype":"locality"
},
  "geometry": {"coordinates":[-57.20176,-31.28066],"type":"Point"}
}