{
  "type": "Feature",
  "properties": {
    "gn:admin1_code":"11",
    "gn:asciiname":"Canada del Pueblo",
    "gn:country_code":"UY",
    "gn:dem":120,
    "gn:feature_class":"P",
    "gn:feature_code":"PPL",
    "gn:name":"Ca\u00f1ada del Pueblo",
    "gn:population":0,
    "gn:timezone":"America/Montevideo",
    "iso:country":"UY",
    "wof:name":"Canada del Pueblo",
    "wof:placetype":"locality"
},
  "geometry": {"coordinates":[-57.25,-31.83333],"type":"Point"}
}