{
  "type": "Feature",
  "properties": {
    "iso:country":"UY",
    "qs:gn_pop":0,
    "qs:name":"Villa del Mar",
    "qs:name_adm0":"Uruguay",
    "qs:name_adm1":"Canelones",
    "qs:photos":3,
    "qs:photos_1k":1,
    "qs:photos_9k":1,
    "qs:photos_9r":1,
    "qs:photos_all":3,
    "qs:photos_sr":1,
    "qs:placetype":"Town",
    "qs:pop_sr":"0",
    "qs:woe_adm0":23424979,
    "wof:name":"Villa del Mar",
    "wof:placetype":"locality"
},
  "geometry": {"coordinates":[-55.954828,-34.837265],"type":"Point"}
}