{
  "type": "Feature",
  "properties": {
    "gn:admin1_code":"05",
    "gn:asciiname":"Molles",
    "gn:cc2":"UY",
    "gn:country_code":"UY",
    "gn:dem":124,
    "gn:feature_class":"P",
    "gn:feature_code":"PPL",
    "gn:name":"Molles",
    "gn:population":0,
    "gn:timezone":"America/Montevideo",
    "iso:country":"UY",
    "name:cat_x_preferred":[
        "Carlos Reyles"
    ],
    "name:ceb_x_preferred":[
        "Molles"
    ],
    "name:deu_x_preferred":[
        "Carlos Reyles"
    ],
    "name:fra_x_preferred":[
        "Carlos Reyles"
    ],
    "name:hye_x_preferred":[
        "\u053f\u0561\u0580\u056c\u0578\u057d \u054c\u0565\u0575\u056c\u0565\u057d"
    ],
    "name:nor_x_preferred":[
        "Carlos Reyles"
    ],
    "name:rus_x_preferred":[
        "\u041a\u0430\u0440\u043b\u043e\u0441-\u0420\u0435\u0439\u043b\u0435\u0441"
    ],
    "name:spa_x_preferred":[
        "Carlos Reyles"
    ],
    "wof:name":"Molles",
    "wof:placetype":"locality"
},
  "geometry": {"coordinates":[-56.48333,-33.05],"type":"Point"}
}