{
  "type": "Feature",
  "properties": {
    "gn:admin1_code":"05",
    "gn:asciiname":"Molles",
    "gn:cc2":"UY",
    "gn:country_code":"UY",
    "gn:dem":124,
    "gn:feature_class":"P",
    "gn:feature_code":"PPL",
    "gn:name":"Molles",
    "gn:population":0,
    "gn:timezone":"America/Montevideo",
    "iso:country":"UY",
    "name:und_x_variant":[
        "Carlos Reyles",
        "Molles"
    ],
    "wof:name":"Molles",
    "wof:placetype":"locality"
},
  "geometry": {"coordinates":[-56.48333,-33.05],"type":"Point"}
}