{
  "type": "Feature",
  "properties": {
    "iso:country":"UY",
    "name:cat_x_preferred":[
        "Cerro Colorado"
    ],
    "name:deu_x_preferred":[
        "Cerro Colorado"
    ],
    "name:eng_x_preferred":[
        "Alejandro Gallinal"
    ],
    "name:fas_x_preferred":[
        "\u0627\u0644\u062c\u0627\u0646\u062f\u0631\u0648 \u06af\u0627\u0644\u06cc\u0646\u0627\u0644"
    ],
    "name:fra_x_preferred":[
        "Cerro Colorado"
    ],
    "name:hye_x_preferred":[
        "\u0531\u056c\u0565\u056d\u0561\u0576\u0564\u0580\u0578 \u0533\u0561\u056c\u0575\u056b\u0576\u0561\u056c"
    ],
    "name:nld_x_preferred":[
        "Alejandro Gallinal"
    ],
    "name:nob_x_preferred":[
        "Alejandro Gallinal"
    ],
    "name:pol_x_preferred":[
        "Alejandro Gallinal"
    ],
    "name:rus_x_preferred":[
        "\u0410\u043b\u0435\u0445\u0430\u043d\u0434\u0440\u043e-\u0413\u0430\u043b\u043b\u0438\u043d\u0430\u043b\u044c"
    ],
    "name:spa_x_preferred":[
        "Alejandro Gallinal"
    ],
    "qs:gn_country":"UY",
    "qs:gn_fcode":"PPL",
    "qs:gn_pop":1354,
    "qs:name":"Cerro Colorado",
    "qs:name_adm0":"Uruguay",
    "qs:name_adm1":"Florida",
    "qs:photos":0,
    "qs:photos_1k":0,
    "qs:photos_9k":1,
    "qs:photos_9r":1,
    "qs:photos_all":2,
    "qs:photos_sr":0,
    "qs:placetype":"Town",
    "qs:pop_sr":"3",
    "qs:woe_adm0":23424979,
    "wd:wordcount":76,
    "wof:name":"Cerro Colorado",
    "wof:placetype":"locality",
    "wof:population":1354
},
  "geometry": {"coordinates":[-55.55,-33.86667],"type":"Point"}
}