{
  "type": "Feature",
  "properties": {
    "gn:admin1_code":"05",
    "gn:asciiname":"Maria Cejas",
    "gn:cc2":"UY",
    "gn:country_code":"UY",
    "gn:dem":117,
    "gn:feature_class":"P",
    "gn:feature_code":"PPL",
    "gn:name":"Mar\u00eda Cejas",
    "gn:population":0,
    "gn:timezone":"America/Montevideo",
    "iso:country":"UY",
    "name:und_x_variant":[
        "Arroyo Mar\u00eda Cejas",
        "Mar\u00eda Cejas"
    ],
    "wof:name":"Maria Cejas",
    "wof:placetype":"locality"
},
  "geometry": {"coordinates":[-56.18333000000001,-33.08333],"type":"Point"}
}