{
  "type": "Feature",
  "properties": {
    "iso:country":"UY",
    "name:cat_x_preferred":[
        "Tupamba\u00e9"
    ],
    "name:ceb_x_preferred":[
        "Tupamba\u00e9"
    ],
    "name:deu_x_preferred":[
        "Tupamba\u00e9"
    ],
    "name:eng_x_preferred":[
        "Tupamba\u00e9"
    ],
    "name:fra_x_preferred":[
        "Tupamba\u00e9"
    ],
    "name:hrv_x_preferred":[
        "Tupamba\u00e9"
    ],
    "name:hye_x_preferred":[
        "\u054f\u0578\u0582\u057a\u0561\u0574\u0562\u0565"
    ],
    "name:nld_x_preferred":[
        "Tupamba\u00e9"
    ],
    "name:nob_x_preferred":[
        "Tupamba\u00e9"
    ],
    "name:nor_x_preferred":[
        "Tupamba\u00e9"
    ],
    "name:rus_x_preferred":[
        "\u0422\u0443\u043f\u0430\u043c\u0431\u0435"
    ],
    "name:spa_x_preferred":[
        "Tupamba\u00e9"
    ],
    "name:zho_x_preferred":[
        "\u5716\u6f58\u5df4\u57c3"
    ],
    "qs:gn_country":"UY",
    "qs:gn_fcode":"PPL",
    "qs:gn_pop":1189,
    "qs:name":"Tupamba\u00e9",
    "qs:name_adm0":"Uruguay",
    "qs:name_adm1":"Cerro Largo",
    "qs:photos":0,
    "qs:photos_1k":0,
    "qs:photos_9k":1,
    "qs:photos_9r":1,
    "qs:photos_all":1,
    "qs:photos_sr":0,
    "qs:placetype":"Town",
    "qs:pop_sr":"3",
    "qs:woe_adm0":23424979,
    "wd:wordcount":144,
    "wof:name":"Tupamba\u00e9",
    "wof:placetype":"locality",
    "wof:population":1189
},
  "geometry": {"coordinates":[-54.76667,-32.83333],"type":"Point"}
}