{
  "type": "Feature",
  "properties": {
    "gn:admin1_code":"02",
    "gn:admin2_code":"07",
    "gn:asciiname":"Rincon del Colorado",
    "gn:country_code":"UY",
    "gn:dem":30,
    "gn:feature_class":"P",
    "gn:feature_code":"PPL",
    "gn:name":"Rinc\u00f3n del Colorado",
    "gn:population":0,
    "gn:timezone":"America/Montevideo",
    "iso:country":"UY",
    "name:spa_x_preferred":[
        "Rinc\u00f3n del Colorado"
    ],
    "wof:name":"Rincon del Colorado",
    "wof:placetype":"locality"
},
  "geometry": {"coordinates":[-56.33291,-34.68893],"type":"Point"}
}