{
  "type": "Feature",
  "properties": {
    "gn:admin1_code":"17",
    "gn:asciiname":"Agraciada",
    "gn:country_code":"UY",
    "gn:dem":62,
    "gn:feature_class":"P",
    "gn:feature_code":"PPL",
    "gn:name":"Agraciada",
    "gn:population":0,
    "gn:timezone":"America/Montevideo",
    "iso:country":"UY",
    "name:cat_x_preferred":[
        "Agraciada"
    ],
    "name:ceb_x_preferred":[
        "Agraciada"
    ],
    "name:deu_x_preferred":[
        "Agraciada"
    ],
    "name:fas_x_preferred":[
        "\u0627\u06af\u0631\u0627\u0633\u06cc\u062f\u0627"
    ],
    "name:fra_x_preferred":[
        "Agraciada"
    ],
    "name:nor_x_preferred":[
        "Agraciada"
    ],
    "name:spa_x_preferred":[
        "Agraciada"
    ],
    "name:und_x_variant":[
        "Pueblo la Agraciada",
        "Agraciada"
    ],
    "name:urd_x_preferred":[
        "\u0622\u06af\u0631\u0627\u0633\u06cc\u0627\u062f\u0627"
    ],
    "wof:name":"Agraciada",
    "wof:placetype":"locality"
},
  "geometry": {"coordinates":[-58.26669,-33.80981],"type":"Point"}
}