{
  "type": "Feature",
  "properties": {
    "gn:admin1_code":"14",
    "gn:admin2_code":"01",
    "gn:asciiname":"Barra de Valizas",
    "gn:country_code":"UY",
    "gn:dem":2,
    "gn:feature_class":"P",
    "gn:feature_code":"PPL",
    "gn:name":"Barra de Valizas",
    "gn:population":0,
    "gn:timezone":"America/Montevideo",
    "iso:country":"UY",
    "name:spa_x_preferred":[
        "Barra de Valizas"
    ],
    "name:und_x_variant":[
        "Balizas",
        "Valizas"
    ],
    "wof:name":"Barra de Valizas",
    "wof:placetype":"locality"
},
  "geometry": {"coordinates":[-53.79581999999999,-34.33611],"type":"Point"}
}