{
  "type": "Feature",
  "properties": {
    "gn:admin1_code":"13",
    "gn:asciiname":"Cerro Pelado del Este",
    "gn:country_code":"UY",
    "gn:dem":200,
    "gn:feature_class":"P",
    "gn:feature_code":"PPL",
    "gn:name":"Cerro Pelado del Este",
    "gn:population":0,
    "gn:timezone":"America/Montevideo",
    "iso:country":"UY",
    "wof:name":"Cerro Pelado del Este",
    "wof:placetype":"locality"
},
  "geometry": {"coordinates":[-55.15377,-31.47055],"type":"Point"}
}