{
  "type": "Feature",
  "properties": {
    "gn:admin1_code":"14",
    "gn:admin2_code":"01",
    "gn:asciiname":"Aguas Dulces",
    "gn:country_code":"UY",
    "gn:dem":6,
    "gn:feature_class":"P",
    "gn:feature_code":"PPL",
    "gn:name":"Aguas Dulces",
    "gn:population":0,
    "gn:timezone":"America/Montevideo",
    "iso:country":"UY",
    "name:ceb_x_preferred":[
        "Aguas Dulces"
    ],
    "name:deu_x_preferred":[
        "Aguas Dulces"
    ],
    "name:fas_x_preferred":[
        "\u0627\u06af\u0648\u0627\u0633 \u062f\u0627\u0644\u0633\u06cc\u0633"
    ],
    "name:fra_x_preferred":[
        "Aguas Dulces"
    ],
    "name:nor_x_preferred":[
        "Aguas Dulces"
    ],
    "name:spa_x_preferred":[
        "Aguas Dulces"
    ],
    "name:und_x_variant":[
        "Agua Dulce",
        "Balneario Agua Dulce",
        "Aguas Dulces"
    ],
    "name:urd_x_preferred":[
        "\u0627\u06af\u0648\u0627\u0633 \u062f\u0627\u0644\u0633\u06cc\u0633"
    ],
    "wof:name":"Aguas Dulces",
    "wof:placetype":"locality"
},
  "geometry": {"coordinates":[-53.78206,-34.27448],"type":"Point"}
}