{
  "type": "Feature",
  "properties": {
    "gn:country":"UY",
    "gn:fcode":"PPL",
    "gn:pop":15924,
    "iso:country":"UY",
    "name:fas_x_preferred":[
        "\u06cc\u0627\u0646\u06af\u060c \u0627\u0631\u0648\u06af\u0648\u0626\u0647"
    ],
    "name:hye_x_preferred":[
        "\u0545\u0561\u0576\u0563"
    ],
    "name:kat_x_preferred":[
        "\u10d8\u10d0\u10dc\u10d2\u10d8"
    ],
    "name:lit_x_preferred":[
        "Jangas"
    ],
    "name:rus_x_preferred":[
        "\u042f\u043d\u0433"
    ],
    "name:urd_x_preferred":[
        "\u06cc\u0646\u06af\u060c \u06cc\u0648\u0631\u0627\u06af\u0648\u0626\u06d2"
    ],
    "name:zho_x_preferred":[
        "\u694a\u683c"
    ],
    "qs:name":"Young",
    "qs:photos_9r":0,
    "qs:photos_sr":0,
    "qs:pop_sr":"6",
    "wd:wordcount":424,
    "wof:name":"Young",
    "wof:placetype":"locality",
    "wof:population":15924
},
  "geometry": {"coordinates":[-57.63333,-32.68333],"type":"Point"}
}