{
  "type": "Feature",
  "properties": {
    "gn:admin1_code":"03",
    "gn:admin2_code":"09",
    "gn:asciiname":"Fraile Muerto",
    "gn:cc2":"UY",
    "gn:country_code":"UY",
    "gn:dem":130,
    "gn:feature_class":"P",
    "gn:feature_code":"PPL",
    "gn:name":"Fraile Muerto",
    "gn:population":0,
    "gn:timezone":"America/Montevideo",
    "iso:country":"UY",
    "name:und_x_variant":[
        "Frayle Muerto",
        "Fraile Muerto"
    ],
    "wof:name":"Fraile Muerto",
    "wof:placetype":"locality"
},
  "geometry": {"coordinates":[-54.53333000000001,-32.51667],"type":"Point"}
}