{
  "type": "Feature",
  "properties": {
    "gn:admin1_code":"03",
    "gn:admin2_code":"09",
    "gn:asciiname":"Fraile Muerto",
    "gn:cc2":"UY",
    "gn:country_code":"UY",
    "gn:dem":130,
    "gn:feature_class":"P",
    "gn:feature_code":"PPL",
    "gn:name":"Fraile Muerto",
    "gn:population":0,
    "gn:timezone":"America/Montevideo",
    "iso:country":"UY",
    "name:cat_x_preferred":[
        "Fraile Muerto"
    ],
    "name:ceb_x_preferred":[
        "Fraile Muerto"
    ],
    "name:deu_x_preferred":[
        "Fraile Muerto"
    ],
    "name:fra_x_preferred":[
        "Fraile Muerto"
    ],
    "name:hrv_x_preferred":[
        "Fraile Muerto"
    ],
    "name:ita_x_preferred":[
        "Fraile Muerto"
    ],
    "name:nor_x_preferred":[
        "Fraile Muerto"
    ],
    "name:rus_x_preferred":[
        "\u0424\u0440\u0430\u0439\u043b\u0435-\u041c\u0443\u044d\u0440\u0442\u043e"
    ],
    "name:spa_x_preferred":[
        "Fraile Muerto"
    ],
    "name:und_x_variant":[
        "Frayle Muerto",
        "Fraile Muerto"
    ],
    "name:zho_x_preferred":[
        "\u5f17\u8cf4\u840a\u7a46\u57c3\u723e\u6258"
    ],
    "wof:name":"Fraile Muerto",
    "wof:placetype":"locality"
},
  "geometry": {"coordinates":[-54.53333000000001,-32.51667],"type":"Point"}
}