{
  "type": "Feature",
  "properties": {
    "gn:admin1_code":"19",
    "gn:admin2_code":"02",
    "gn:asciiname":"El Catete",
    "gn:country_code":"UY",
    "gn:dem":115,
    "gn:feature_class":"P",
    "gn:feature_code":"PPL",
    "gn:name":"El Catete",
    "gn:population":0,
    "gn:timezone":"America/Montevideo",
    "iso:country":"UY",
    "wof:name":"El Catete",
    "wof:placetype":"locality"
},
  "geometry": {"coordinates":[-54.21666999999999,-32.95],"type":"Point"}
}