{
  "type": "Feature",
  "properties": {
    "gn:admin1_code":"17",
    "gn:asciiname":"Palo Solo",
    "gn:country_code":"UY",
    "gn:dem":92,
    "gn:feature_class":"P",
    "gn:feature_code":"PPL",
    "gn:name":"Palo Solo",
    "gn:population":0,
    "gn:timezone":"America/Montevideo",
    "iso:country":"UY",
    "name:spa_x_preferred":[
        "Palo Solo"
    ],
    "wof:name":"Palo Solo",
    "wof:placetype":"locality"
},
  "geometry": {"coordinates":[-58.02352,-33.82885],"type":"Point"}
}