{
  "type": "Feature",
  "properties": {
    "gn:admin1_code":"09",
    "gn:admin2_code":"07",
    "gn:asciiname":"Manantiales",
    "gn:country_code":"UY",
    "gn:dem":23,
    "gn:feature_class":"P",
    "gn:feature_code":"PPL",
    "gn:name":"Manantiales",
    "gn:population":0,
    "gn:timezone":"America/Montevideo",
    "iso:country":"UY",
    "name:cat_x_preferred":[
        "Manantiales"
    ],
    "name:ceb_x_preferred":[
        "Manantiales"
    ],
    "name:deu_x_preferred":[
        "Manantiales"
    ],
    "name:fra_x_preferred":[
        "Manantiales"
    ],
    "name:spa_x_preferred":[
        "Manantiales"
    ],
    "name:swe_x_preferred":[
        "Manantiales"
    ],
    "name:und_x_variant":[
        "Playa Manantiales"
    ],
    "wof:name":"Manantiales",
    "wof:placetype":"locality"
},
  "geometry": {"coordinates":[-54.82555,-34.90508],"type":"Point"}
}