{
  "type": "Feature",
  "properties": {
    "iso:country":"UY",
    "qs:gn_pop":0,
    "qs:name":"Riachuelo",
    "qs:name_adm0":"Uruguay",
    "qs:name_adm1":"Colonia",
    "qs:photos":130,
    "qs:photos_1k":26,
    "qs:photos_9k":1,
    "qs:photos_9r":3,
    "qs:photos_all":130,
    "qs:photos_sr":3,
    "qs:placetype":"Town",
    "qs:pop_sr":"0",
    "qs:woe_adm0":23424979,
    "wof:name":"Riachuelo",
    "wof:placetype":"locality"
},
  "geometry": {"coordinates":[-57.729034,-34.446202],"type":"Point"}
}