{
  "type": "Feature",
  "properties": {
    "iso:country":"UY",
    "name:ceb_x_preferred":[
        "Riachuelo"
    ],
    "name:deu_x_preferred":[
        "Riachuelo"
    ],
    "name:fra_x_preferred":[
        "Riachuelo"
    ],
    "name:ita_x_preferred":[
        "Riachuelo"
    ],
    "name:nld_x_preferred":[
        "Riachuelo"
    ],
    "name:nor_x_preferred":[
        "Riachuelo"
    ],
    "name:por_x_preferred":[
        "Riachuelo"
    ],
    "name:rus_x_preferred":[
        "\u0420\u0438\u0430\u0448\u0443\u044d\u043b\u0443"
    ],
    "name:spa_x_preferred":[
        "Riachuelo"
    ],
    "name:swe_x_preferred":[
        "Riachuelo"
    ],
    "name:vol_x_preferred":[
        "Riachuelo"
    ],
    "qs:gn_pop":0,
    "qs:name":"Riachuelo",
    "qs:name_adm0":"Uruguay",
    "qs:name_adm1":"Colonia",
    "qs:photos":130,
    "qs:photos_1k":26,
    "qs:photos_9k":1,
    "qs:photos_9r":3,
    "qs:photos_all":130,
    "qs:photos_sr":3,
    "qs:placetype":"Town",
    "qs:pop_sr":"0",
    "qs:woe_adm0":23424979,
    "wof:name":"Riachuelo",
    "wof:placetype":"locality"
},
  "geometry": {"coordinates":[-57.729034,-34.446202],"type":"Point"}
}