{
  "type": "Feature",
  "properties": {
    "gn:admin1_code":"11",
    "gn:asciiname":"El Chaco",
    "gn:country_code":"UY",
    "gn:dem":109,
    "gn:feature_class":"P",
    "gn:feature_code":"PPL",
    "gn:name":"El Chaco",
    "gn:population":0,
    "gn:timezone":"America/Montevideo",
    "iso:country":"UY",
    "name:spa_x_preferred":[
        "El Chaco"
    ],
    "wof:name":"El Chaco",
    "wof:placetype":"locality"
},
  "geometry": {"coordinates":[-57.5133,-31.95896],"type":"Point"}
}