{
  "type": "Feature",
  "properties": {
    "gn:admin1_code":"02",
    "gn:admin2_code":"08",
    "gn:asciiname":"Lagomar",
    "gn:country_code":"UY",
    "gn:dem":10,
    "gn:feature_class":"P",
    "gn:feature_code":"PPL",
    "gn:name":"Lagomar",
    "gn:population":0,
    "gn:timezone":"America/Montevideo",
    "iso:country":"UY",
    "wof:name":"Lagomar",
    "wof:placetype":"locality"
},
  "geometry": {"coordinates":[-55.9832,-34.83768],"type":"Point"}
}