{
  "type": "Feature",
  "properties": {
    "gn:admin1_code":"18",
    "gn:asciiname":"Poblado La Humedad",
    "gn:cc2":"UY",
    "gn:country_code":"UY",
    "gn:dem":121,
    "gn:feature_class":"P",
    "gn:feature_code":"PPL",
    "gn:name":"Poblado La Humedad",
    "gn:population":0,
    "gn:timezone":"America/Montevideo",
    "iso:country":"UY",
    "name:und_x_variant":[
        "La Humedad",
        "Poblado La Humedad"
    ],
    "wof:name":"Poblado La Humedad",
    "wof:placetype":"locality"
},
  "geometry": {"coordinates":[-54.86666999999999,-32.05],"type":"Point"}
}