{
  "type": "Feature",
  "properties": {
    "gn:admin1_code":"04",
    "gn:admin2_code":"04",
    "gn:asciiname":"Rosario y Colla",
    "gn:country_code":"UY",
    "gn:dem":78,
    "gn:feature_class":"P",
    "gn:feature_code":"PPL",
    "gn:name":"Rosario y Colla",
    "gn:population":0,
    "gn:timezone":"America/Montevideo",
    "iso:country":"UY",
    "name:spa_x_preferred":[
        "Rosario y Colla"
    ],
    "wof:name":"Rosario y Colla",
    "wof:placetype":"locality"
},
  "geometry": {"coordinates":[-57.33503,-34.27533],"type":"Point"}
}