{
  "type": "Feature",
  "properties": {
    "gn:admin1_code":"07",
    "gn:asciiname":"Goni",
    "gn:cc2":"UY",
    "gn:country_code":"UY",
    "gn:dem":110,
    "gn:feature_class":"P",
    "gn:feature_code":"PPL",
    "gn:name":"Go\u00f1i",
    "gn:population":0,
    "gn:timezone":"America/Montevideo",
    "iso:country":"UY",
    "name:und_x_variant":[
        "Estaci\u00f3n Go\u00f1i",
        "Go\u00f1i"
    ],
    "wof:name":"Goni",
    "wof:placetype":"locality"
},
  "geometry": {"coordinates":[-56.4129,-33.52032],"type":"Point"}
}