{
  "type": "Feature",
  "properties": {
    "gn:admin1_code":"04",
    "gn:asciiname":"Blanca Arena",
    "gn:country_code":"UY",
    "gn:dem":15,
    "gn:feature_class":"P",
    "gn:feature_code":"PPL",
    "gn:name":"Blanca Arena",
    "gn:population":0,
    "gn:timezone":"America/Montevideo",
    "iso:country":"UY",
    "name:spa_x_preferred":[
        "Blanca Arena"
    ],
    "wof:name":"Blanca Arena",
    "wof:placetype":"locality"
},
  "geometry": {"coordinates":[-57.29673,-34.43565],"type":"Point"}
}