{
  "type": "Feature",
  "properties": {
    "gn:admin1_code":"19",
    "gn:admin2_code":"01",
    "gn:asciiname":"Medina",
    "gn:country_code":"UY",
    "gn:dem":105,
    "gn:feature_class":"P",
    "gn:feature_code":"PPL",
    "gn:name":"Medina",
    "gn:population":0,
    "gn:timezone":"America/Montevideo",
    "iso:country":"UY",
    "wof:name":"Medina",
    "wof:placetype":"locality"
},
  "geometry": {"coordinates":[-54.83333,-33.11667],"type":"Point"}
}