{
  "type": "Feature",
  "properties": {
    "gn:admin1_code":"01",
    "gn:admin2_code":"02",
    "gn:asciiname":"Ingeniero Agronomo Alfredo Mones Quintela",
    "gn:country_code":"UY",
    "gn:dem":51,
    "gn:feature_class":"P",
    "gn:feature_code":"PPL",
    "gn:name":"Ingeniero Agr\u00f3nomo Alfredo Mones Quintela",
    "gn:population":0,
    "gn:timezone":"America/Montevideo",
    "iso:country":"UY",
    "name:spa_x_preferred":[
        "Calpica Itacumb\u00fa"
    ],
    "name:spa_x_variant":[
        "Ingeniero Agr\u00f3nomo Alfredo Mones Quintela"
    ],
    "wof:name":"Ingeniero Agronomo Alfredo Mones Quintela",
    "wof:placetype":"locality"
},
  "geometry": {"coordinates":[-57.66376,-30.37375],"type":"Point"}
}