{
  "type": "Feature",
  "properties": {
    "gn:admin1_code":"19",
    "gn:asciiname":"Canada Chica",
    "gn:country_code":"UY",
    "gn:dem":15,
    "gn:feature_class":"P",
    "gn:feature_code":"PPL",
    "gn:name":"Ca\u00f1ada Chica",
    "gn:population":0,
    "gn:timezone":"America/Montevideo",
    "iso:country":"UY",
    "name:spa_x_preferred":[
        "Ca\u00f1ada Chica"
    ],
    "wof:name":"Canada Chica",
    "wof:placetype":"locality"
},
  "geometry": {"coordinates":[-53.98169,-33.31698],"type":"Point"}
}