{
  "type": "Feature",
  "properties": {
    "iso:country":"UY",
    "name:cat_x_preferred":[
        "Tarariras"
    ],
    "name:ceb_x_preferred":[
        "Tarariras"
    ],
    "name:deu_x_preferred":[
        "Tarariras"
    ],
    "name:eng_x_preferred":[
        "Tarariras"
    ],
    "name:fas_x_preferred":[
        "\u062a\u0627\u0631\u0627\u0631\u06cc\u0631\u0627\u0633"
    ],
    "name:fra_x_preferred":[
        "Tarariras"
    ],
    "name:ita_x_preferred":[
        "Tarariras"
    ],
    "name:nld_x_preferred":[
        "Tarariras"
    ],
    "name:nob_x_preferred":[
        "Tarariras"
    ],
    "name:nor_x_preferred":[
        "Tarariras"
    ],
    "name:pol_x_preferred":[
        "Tarariras"
    ],
    "name:por_x_preferred":[
        "Tarariras"
    ],
    "name:rus_x_preferred":[
        "\u0422\u0430\u0440\u0430\u0440\u0438\u0440\u0430\u0441"
    ],
    "name:spa_x_preferred":[
        "Tarariras"
    ],
    "name:und_x_variant":[
        "J. Su\u00e1rez"
    ],
    "name:urd_x_preferred":[
        "\u062a\u0627\u0631\u0627\u0631\u06cc\u0631\u0627\u0633"
    ],
    "name:zho_x_preferred":[
        "\u5854\u62c9\u91cc\u62c9\u65af"
    ],
    "qs:gn_country":"UY",
    "qs:gn_fcode":"PPL",
    "qs:gn_pop":6069,
    "qs:name":"Tarariras",
    "qs:name_adm0":"Uruguay",
    "qs:name_adm1":"Colonia",
    "qs:photos":0,
    "qs:photos_1k":0,
    "qs:photos_9k":1,
    "qs:photos_9r":4,
    "qs:photos_all":185,
    "qs:photos_sr":0,
    "qs:placetype":"Town",
    "qs:pop_sr":"5",
    "qs:woe_adm0":23424979,
    "wd:wordcount":294,
    "wof:name":"Tarariras",
    "wof:placetype":"locality",
    "wof:population":6069
},
  "geometry": {"coordinates":[-57.61667,-34.28333],"type":"Point"}
}