{
  "type": "Feature",
  "properties": {
    "gn:admin1_code":"15",
    "gn:admin2_code":"04",
    "gn:asciiname":"Cambara",
    "gn:country_code":"UY",
    "gn:dem":200,
    "gn:feature_class":"P",
    "gn:feature_code":"PPL",
    "gn:name":"Cambar\u00e1",
    "gn:population":0,
    "gn:timezone":"America/Montevideo",
    "iso:country":"UY",
    "wof:name":"Cambara",
    "wof:placetype":"locality"
},
  "geometry": {"coordinates":[-56.46666999999999,-31.11667000000001],"type":"Point"}
}