{
  "type": "Feature",
  "properties": {
    "gn:admin1_code":"19",
    "gn:asciiname":"El Bellaco",
    "gn:country_code":"UY",
    "gn:dem":122,
    "gn:feature_class":"P",
    "gn:feature_code":"PPL",
    "gn:name":"El Bellaco",
    "gn:population":0,
    "gn:timezone":"America/Montevideo",
    "iso:country":"UY",
    "name:spa_x_preferred":[
        "El Bellaco"
    ],
    "wof:name":"El Bellaco",
    "wof:placetype":"locality"
},
  "geometry": {"coordinates":[-54.55114,-33.43724],"type":"Point"}
}