{
  "type": "Feature",
  "properties": {
    "gn:gn_country":"UY",
    "gn:gn_fcode":"PPLX",
    "gn:gn_pop":0,
    "iso:country":"UY",
    "name:cat_x_preferred":[
        "Reducto"
    ],
    "name:deu_x_preferred":[
        "Reducto"
    ],
    "name:eng_x_preferred":[
        "Reducto"
    ],
    "name:fra_x_preferred":[
        "Reducto"
    ],
    "name:nld_x_preferred":[
        "Reducto"
    ],
    "name:spa_x_preferred":[
        "Reducto"
    ],
    "name:unk_x_variant":[
        "Reducto"
    ],
    "qs:gn_adm0_cc":"US",
    "qs:gn_fcode":"PPLX",
    "qs:gn_local":5038018,
    "qs:gn_namadm1":"10",
    "qs:gn_name":"Reducto",
    "qs:local_max":9496,
    "qs:local_sum":30959,
    "qs:localhoods":17,
    "qs:name":"Reducto",
    "qs:name_adm0":"Uruguay",
    "qs:name_adm1":"Montevideo",
    "qs:name_local":"Montevideo",
    "qs:photo_max":242,
    "qs:photo_sum":652,
    "qs:placetype":"Suburb",
    "qs:quad_count":21,
    "qs:woe_adm0":23424979,
    "qs:woe_adm1":2347649,
    "qs:woe_adm2":0,
    "qs:woe_lau":0,
    "qs:woe_local":468052,
    "qs:woe_ver":"7.10.0",
    "qs_pg:aaroncc":"UY",
    "qs_pg:gn_country":"UY",
    "qs_pg:gn_fcode":"PPLX",
    "qs_pg:gn_pop":0,
    "qs_pg:name":"Reducto",
    "qs_pg:name_adm0":"Uruguay",
    "qs_pg:name_adm1":"Montevideo",
    "qs_pg:photos":518,
    "qs_pg:photos_1k":105,
    "qs_pg:photos_9k":2,
    "qs_pg:photos_9r":5,
    "qs_pg:photos_all":518,
    "qs_pg:photos_sr":7,
    "qs_pg:pop_sr":0,
    "qs_pg:qs_pg_placetype":"neighbourhood",
    "qs_pg:qs_pg_placetype_gp":"Suburb",
    "qs_pg:woe_adm0":23424979,
    "wd:wordcount":200,
    "wof:lang":[
        "spa"
    ],
    "wof:name":"Reducto",
    "wof:placetype":"neighbourhood"
},
  "geometry": {"coordinates":[-56.182881,-34.892322],"type":"Point"}
}