{
  "type": "Feature",
  "properties": {
    "gn:admin1_code":"08",
    "gn:asciiname":"Solis",
    "gn:country_code":"UY",
    "gn:dem":106,
    "gn:feature_class":"P",
    "gn:feature_code":"PPL",
    "gn:name":"Sol\u00eds",
    "gn:population":0,
    "gn:timezone":"America/Montevideo",
    "iso:country":"UY",
    "wof:name":"Solis",
    "wof:placetype":"locality"
},
  "geometry": {"coordinates":[-55.45,-34.33333],"type":"Point"}
}