{
  "type": "Feature",
  "properties": {
    "gn:admin1_code":"15",
    "gn:admin2_code":"03",
    "gn:asciiname":"Bordenave",
    "gn:country_code":"UY",
    "gn:dem":198,
    "gn:feature_class":"P",
    "gn:feature_code":"PPL",
    "gn:name":"Bordenave",
    "gn:population":0,
    "gn:timezone":"America/Montevideo",
    "iso:country":"UY",
    "name:spa_x_preferred":[
        "Bordenave"
    ],
    "wof:name":"Bordenave",
    "wof:placetype":"locality"
},
  "geometry": {"coordinates":[-56.6868,-31.08354000000001],"type":"Point"}
}