{
  "type": "Feature",
  "properties": {
    "iso:country":"UY",
    "name:cat_x_preferred":[
        "Cardal"
    ],
    "name:ceb_x_preferred":[
        "Cardal"
    ],
    "name:deu_x_preferred":[
        "Cardal"
    ],
    "name:eng_x_preferred":[
        "Cardal"
    ],
    "name:fra_x_preferred":[
        "Cardal"
    ],
    "name:ita_x_preferred":[
        "Cardal"
    ],
    "name:nld_x_preferred":[
        "Cardal"
    ],
    "name:nob_x_preferred":[
        "Cardal"
    ],
    "name:nor_x_preferred":[
        "Cardal"
    ],
    "name:rus_x_preferred":[
        "\u041a\u0430\u0440\u0434\u0430\u043b\u044c"
    ],
    "name:spa_x_preferred":[
        "Cardal"
    ],
    "qs:gn_country":"UY",
    "qs:gn_fcode":"PPL",
    "qs:gn_pop":1291,
    "qs:name":"Cardal",
    "qs:name_adm0":"Uruguay",
    "qs:name_adm1":"Florida",
    "qs:photos":0,
    "qs:photos_1k":0,
    "qs:photos_9k":1,
    "qs:photos_9r":1,
    "qs:photos_all":1,
    "qs:photos_sr":0,
    "qs:placetype":"Town",
    "qs:pop_sr":"3",
    "qs:woe_adm0":23424979,
    "wd:wordcount":467,
    "wof:name":"Cardal",
    "wof:placetype":"locality",
    "wof:population":1291
},
  "geometry": {"coordinates":[-56.38889,-34.29056],"type":"Point"}
}