{
  "type": "Feature",
  "properties": {
    "gn:admin1_code":"17",
    "gn:admin2_code":"04",
    "gn:asciiname":"Coquimbo",
    "gn:country_code":"UY",
    "gn:dem":68,
    "gn:feature_class":"P",
    "gn:feature_code":"PPL",
    "gn:name":"Coquimbo",
    "gn:population":0,
    "gn:timezone":"America/Montevideo",
    "iso:country":"UY",
    "name:ara_x_preferred":[
        "\u0643\u0648\u0643\u064a\u0645\u0628\u0648"
    ],
    "name:ast_x_preferred":[
        "Coquimbo"
    ],
    "name:aym_x_preferred":[
        "Coquimbo"
    ],
    "name:aze_x_preferred":[
        "Coquimbo"
    ],
    "name:bul_x_preferred":[
        "\u041a\u043e\u043a\u0438\u043c\u0431\u043e"
    ],
    "name:ceb_x_preferred":[
        "Coquimbo"
    ],
    "name:ces_x_preferred":[
        "Coquimbo"
    ],
    "name:dan_x_preferred":[
        "Coquimbo"
    ],
    "name:deu_x_preferred":[
        "Coquimbo"
    ],
    "name:epo_x_preferred":[
        "Coquimbo"
    ],
    "name:eus_x_preferred":[
        "Coquimbo"
    ],
    "name:fas_x_preferred":[
        "\u06a9\u0648\u06a9\u06cc\u0645\u0628\u0648"
    ],
    "name:fra_x_preferred":[
        "Coquimbo"
    ],
    "name:glg_x_preferred":[
        "Coquimbo"
    ],
    "name:hat_x_preferred":[
        "Coquimbo"
    ],
    "name:hun_x_preferred":[
        "Coquimbo"
    ],
    "name:ind_x_preferred":[
        "Coquimbo"
    ],
    "name:ita_x_preferred":[
        "Coquimbo"
    ],
    "name:jpn_x_preferred":[
        "\u30b3\u30ad\u30f3\u30dc"
    ],
    "name:kor_x_preferred":[
        "\ucf54\ud0b4\ubcf4"
    ],
    "name:lit_x_preferred":[
        "Kokimbas"
    ],
    "name:nld_x_preferred":[
        "Coquimbo"
    ],
    "name:nor_x_preferred":[
        "Coquimbo"
    ],
    "name:oci_x_preferred":[
        "Coquimbo"
    ],
    "name:pol_x_preferred":[
        "Coquimbo"
    ],
    "name:por_x_preferred":[
        "Coquimbo"
    ],
    "name:que_x_preferred":[
        "Kukimpu"
    ],
    "name:rmy_x_preferred":[
        "Coquimbo"
    ],
    "name:ron_x_preferred":[
        "Coquimbo"
    ],
    "name:rus_x_preferred":[
        "\u041a\u043e\u043a\u0438\u043c\u0431\u043e"
    ],
    "name:spa_x_preferred":[
        "Coquimbo"
    ],
    "name:srp_x_preferred":[
        "\u041a\u043e\u043a\u0438\u043c\u0431\u043e"
    ],
    "name:swe_x_preferred":[
        "Coquimbo"
    ],
    "name:tat_x_preferred":[
        "\u041a\u043e\u043a\u0438\u043c\u0431\u043e"
    ],
    "name:tha_x_preferred":[
        "\u0e42\u0e01\u0e01\u0e34\u0e21\u0e42\u0e1a"
    ],
    "name:tur_x_preferred":[
        "Coquimbo"
    ],
    "name:ukr_x_preferred":[
        "\u041a\u043e\u043a\u0456\u043c\u0431\u043e"
    ],
    "name:vol_x_preferred":[
        "Coquimbo"
    ],
    "name:war_x_preferred":[
        "Coquimbo"
    ],
    "name:zho_x_preferred":[
        "\u79d1\u91d1\u535a"
    ],
    "wof:name":"Coquimbo",
    "wof:placetype":"locality"
},
  "geometry": {"coordinates":[-57.73333,-33.45],"type":"Point"}
}