{
  "type": "Feature",
  "properties": {
    "gn:admin1_code":"17",
    "gn:admin2_code":"04",
    "gn:asciiname":"Coquimbo",
    "gn:country_code":"UY",
    "gn:dem":68,
    "gn:feature_class":"P",
    "gn:feature_code":"PPL",
    "gn:name":"Coquimbo",
    "gn:population":0,
    "gn:timezone":"America/Montevideo",
    "iso:country":"UY",
    "wof:name":"Coquimbo",
    "wof:placetype":"locality"
},
  "geometry": {"coordinates":[-57.73333,-33.45],"type":"Point"}
}