{
  "type": "Feature",
  "properties": {
    "gn:country":"UY",
    "gn:fcode":"PPL",
    "gn:population":17973,
    "iso:country":"UY",
    "qs_pg:aaroncc":"UY",
    "qs_pg:gn_country":"UY",
    "qs_pg:gn_fcode":"PPL",
    "qs_pg:gn_pop":17973,
    "qs_pg:name":"Delta del Tigre",
    "qs_pg:photos_9r":0,
    "qs_pg:photos_sr":0,
    "qs_pg:pop_sr":6,
    "qs_pg:qs_pg_placetype":"locality",
    "wof:name":"Delta del Tigre",
    "wof:placetype":"locality",
    "wof:population":17973
},
  "geometry": {"coordinates":[-56.38528,-34.76333],"type":"Point"}
}