{
  "type": "Feature",
  "properties": {
    "gn:admin1_code":"03",
    "gn:admin2_code":"02",
    "gn:asciiname":"Soto",
    "gn:country_code":"UY",
    "gn:dem":130,
    "gn:feature_class":"P",
    "gn:feature_code":"PPL",
    "gn:name":"Soto",
    "gn:population":0,
    "gn:timezone":"America/Montevideo",
    "iso:country":"UY",
    "name:arg_x_preferred":[
        "Soto"
    ],
    "name:ast_x_preferred":[
        "Soto"
    ],
    "name:bre_x_preferred":[
        "Soto"
    ],
    "name:cat_x_preferred":[
        "Soto"
    ],
    "name:ceb_x_preferred":[
        "Soto"
    ],
    "name:deu_x_preferred":[
        "Soto"
    ],
    "name:fin_x_preferred":[
        "Soto"
    ],
    "name:fra_x_preferred":[
        "Soto"
    ],
    "name:glg_x_preferred":[
        "Soto"
    ],
    "name:heb_x_preferred":[
        "\u05e1\u05d5\u05d8\u05d5"
    ],
    "name:ita_x_preferred":[
        "Soto"
    ],
    "name:kor_x_preferred":[
        "\uc18c\ud1a0"
    ],
    "name:nld_x_preferred":[
        "Soto"
    ],
    "name:pol_x_preferred":[
        "Soto"
    ],
    "name:por_x_preferred":[
        "Soto"
    ],
    "name:rus_x_preferred":[
        "\u0421\u043e\u0442\u043e"
    ],
    "name:spa_x_preferred":[
        "Soto"
    ],
    "name:swe_x_preferred":[
        "Soto"
    ],
    "name:ukr_x_preferred":[
        "\u0421\u043e\u0442\u043e"
    ],
    "wof:name":"Soto",
    "wof:placetype":"locality"
},
  "geometry": {"coordinates":[-54.16667,-31.98333],"type":"Point"}
}