{
  "type": "Feature",
  "properties": {
    "gn:admin1_code":"03",
    "gn:admin2_code":"02",
    "gn:asciiname":"Soto",
    "gn:country_code":"UY",
    "gn:dem":130,
    "gn:feature_class":"P",
    "gn:feature_code":"PPL",
    "gn:name":"Soto",
    "gn:population":0,
    "gn:timezone":"America/Montevideo",
    "iso:country":"UY",
    "wof:name":"Soto",
    "wof:placetype":"locality"
},
  "geometry": {"coordinates":[-54.16667,-31.98333],"type":"Point"}
}