{
  "type": "Feature",
  "properties": {
    "gn:admin1_code":"01",
    "gn:admin2_code":"02",
    "gn:asciiname":"Cainsa",
    "gn:country_code":"UY",
    "gn:dem":65,
    "gn:feature_class":"P",
    "gn:feature_code":"PPL",
    "gn:name":"Cainsa",
    "gn:population":0,
    "gn:timezone":"America/Montevideo",
    "iso:country":"UY",
    "name:cat_x_preferred":[
        "Cainsa"
    ],
    "name:ceb_x_preferred":[
        "Cainsa Itacumb\u00fa"
    ],
    "name:deu_x_preferred":[
        "Cainsa"
    ],
    "name:fra_x_preferred":[
        "Cainsa"
    ],
    "name:nor_x_preferred":[
        "Cainsa"
    ],
    "name:spa_x_preferred":[
        "Cainsa Itacumb\u00fa"
    ],
    "name:spa_x_variant":[
        "Cainsa"
    ],
    "wof:name":"Cainsa",
    "wof:placetype":"locality"
},
  "geometry": {"coordinates":[-57.61513000000001,-30.38704],"type":"Point"}
}