{
  "type": "Feature",
  "properties": {
    "gn:admin1_code":"02",
    "gn:admin2_code":"05",
    "gn:asciiname":"Cap. Juan A. Artigas",
    "gn:country_code":"UY",
    "gn:dem":36,
    "gn:feature_class":"P",
    "gn:feature_code":"PPL",
    "gn:name":"Cap. Juan A. Artigas",
    "gn:population":0,
    "gn:timezone":"America/Montevideo",
    "iso:country":"UY",
    "wof:name":"Cap. Juan A. Artigas",
    "wof:placetype":"locality"
},
  "geometry": {"coordinates":[-56.02056,-34.7625],"type":"Point"}
}