{
  "type": "Feature",
  "properties": {
    "gn:admin1_code":"09",
    "gn:admin2_code":"01",
    "gn:asciiname":"Salamanca",
    "gn:country_code":"UY",
    "gn:dem":100,
    "gn:feature_class":"P",
    "gn:feature_code":"PPL",
    "gn:name":"Salamanca",
    "gn:population":0,
    "gn:timezone":"America/Montevideo",
    "iso:country":"UY",
    "wof:name":"Salamanca",
    "wof:placetype":"locality"
},
  "geometry": {"coordinates":[-54.66667,-34.16667],"type":"Point"}
}