{
  "type": "Feature",
  "properties": {
    "gn:admin1_code":"02",
    "gn:admin2_code":"02",
    "gn:asciiname":"Paso Toscas",
    "gn:country_code":"UY",
    "gn:dem":20,
    "gn:feature_class":"P",
    "gn:feature_code":"PPL",
    "gn:name":"Paso Toscas",
    "gn:population":0,
    "gn:timezone":"America/Montevideo",
    "iso:country":"UY",
    "wof:name":"Paso Toscas",
    "wof:placetype":"locality"
},
  "geometry": {"coordinates":[-56.25,-34.45],"type":"Point"}
}