{
  "type": "Feature",
  "properties": {
    "iso:country":"UY",
    "name:ast_x_preferred":[
        "San Antonio"
    ],
    "name:cat_x_preferred":[
        "San Antonio"
    ],
    "name:ceb_x_preferred":[
        "San Antonio"
    ],
    "name:deu_x_preferred":[
        "San Antonio"
    ],
    "name:eng_x_preferred":[
        "San Antonio"
    ],
    "name:fas_x_preferred":[
        "\u0633\u0627\u0646 \u0622\u0646\u062a\u0627\u0631\u06cc\u0648"
    ],
    "name:fra_x_preferred":[
        "San Antonio"
    ],
    "name:heb_x_preferred":[
        "\u05e1\u05df \u05d0\u05e0\u05d8\u05d5\u05e0\u05d9\u05d5"
    ],
    "name:hun_x_preferred":[
        "San Antonio"
    ],
    "name:ita_x_preferred":[
        "San Antonio"
    ],
    "name:nld_x_preferred":[
        "San Antonio"
    ],
    "name:nob_x_preferred":[
        "San Antonio"
    ],
    "name:nor_x_preferred":[
        "San Antonio"
    ],
    "name:spa_x_preferred":[
        "San Antonio"
    ],
    "qs:gn_country":"UY",
    "qs:gn_fcode":"PPL",
    "qs:gn_pop":1453,
    "qs:name":"San Antonio",
    "qs:name_adm0":"Uruguay",
    "qs:name_adm1":"Canelones",
    "qs:photos":0,
    "qs:photos_1k":0,
    "qs:photos_9k":1,
    "qs:photos_9r":1,
    "qs:photos_all":1,
    "qs:photos_sr":0,
    "qs:placetype":"Town",
    "qs:pop_sr":"3",
    "qs:woe_adm0":23424979,
    "wd:wordcount":165,
    "wof:name":"San Antonio",
    "wof:placetype":"locality",
    "wof:population":1453
},
  "geometry": {"coordinates":[-56.07917,-34.44972],"type":"Point"}
}