{
  "type": "Feature",
  "properties": {
    "gn:admin1_code":"09",
    "gn:admin2_code":"07",
    "gn:asciiname":"La Barra",
    "gn:country_code":"UY",
    "gn:dem":31,
    "gn:feature_class":"P",
    "gn:feature_code":"PPL",
    "gn:name":"La Barra",
    "gn:population":0,
    "gn:timezone":"America/Montevideo",
    "iso:country":"UY",
    "name:spa_x_preferred":[
        "La Barra"
    ],
    "wof:name":"La Barra",
    "wof:placetype":"locality"
},
  "geometry": {"coordinates":[-54.85397,-34.91196],"type":"Point"}
}