{
  "type": "Feature",
  "properties": {
    "gn:admin1_code":"11",
    "gn:admin2_code":"02",
    "gn:asciiname":"Merinos",
    "gn:country_code":"UY",
    "gn:dem":171,
    "gn:feature_class":"P",
    "gn:feature_code":"PPL",
    "gn:name":"Merinos",
    "gn:population":0,
    "gn:timezone":"America/Montevideo",
    "iso:country":"UY",
    "name:ceb_x_preferred":[
        "Merinos"
    ],
    "name:deu_x_preferred":[
        "Merinos"
    ],
    "name:fra_x_preferred":[
        "Merinos"
    ],
    "name:hye_x_preferred":[
        "\u0544\u0565\u0580\u056b\u0576\u0578\u057d"
    ],
    "name:nor_x_preferred":[
        "Merinos"
    ],
    "name:rus_x_preferred":[
        "\u041c\u0435\u0440\u0438\u043d\u043e\u0441"
    ],
    "name:spa_x_preferred":[
        "Merinos"
    ],
    "wof:name":"Merinos",
    "wof:placetype":"locality"
},
  "geometry": {"coordinates":[-56.90429,-32.38486],"type":"Point"}
}