{
  "type": "Feature",
  "properties": {
    "gn:admin1_code":"11",
    "gn:admin2_code":"02",
    "gn:asciiname":"Merinos",
    "gn:country_code":"UY",
    "gn:dem":171,
    "gn:feature_class":"P",
    "gn:feature_code":"PPL",
    "gn:name":"Merinos",
    "gn:population":0,
    "gn:timezone":"America/Montevideo",
    "iso:country":"UY",
    "wof:name":"Merinos",
    "wof:placetype":"locality"
},
  "geometry": {"coordinates":[-56.90429,-32.38486],"type":"Point"}
}