{
  "type": "Feature",
  "properties": {
    "gn:admin1_code":"01",
    "gn:asciiname":"Topador",
    "gn:country_code":"UY",
    "gn:dem":159,
    "gn:feature_class":"P",
    "gn:feature_code":"PPL",
    "gn:name":"Topador",
    "gn:population":0,
    "gn:timezone":"America/Montevideo",
    "iso:country":"UY",
    "name:cat_x_preferred":[
        "Topador"
    ],
    "name:ceb_x_preferred":[
        "Topador"
    ],
    "name:deu_x_preferred":[
        "Topador"
    ],
    "name:fra_x_preferred":[
        "Topador"
    ],
    "name:nor_x_preferred":[
        "Topador"
    ],
    "name:spa_x_preferred":[
        "Topador"
    ],
    "name:und_x_variant":[
        "El Topador"
    ],
    "wof:name":"Topador",
    "wof:placetype":"locality"
},
  "geometry": {"coordinates":[-56.82055,-30.29768],"type":"Point"}
}