{
  "type": "Feature",
  "properties": {
    "gn:admin1_code":"14",
    "gn:asciiname":"Los Tacuruses",
    "gn:country_code":"UY",
    "gn:dem":11,
    "gn:feature_class":"P",
    "gn:feature_code":"PPL",
    "gn:name":"Los Tacuruses",
    "gn:population":0,
    "gn:timezone":"America/Montevideo",
    "iso:country":"UY",
    "name:spa_x_preferred":[
        "Los Tacuruses"
    ],
    "wof:name":"Los Tacuruses",
    "wof:placetype":"locality"
},
  "geometry": {"coordinates":[-53.85496,-33.3626],"type":"Point"}
}