{
  "type": "Feature",
  "properties": {
    "gn:admin1_code":"08",
    "gn:asciiname":"Marco de Los Reyes",
    "gn:country_code":"UY",
    "gn:dem":368,
    "gn:feature_class":"P",
    "gn:feature_code":"PPL",
    "gn:name":"Marco de Los Reyes",
    "gn:population":0,
    "gn:timezone":"America/Montevideo",
    "iso:country":"UY",
    "name:spa_x_preferred":[
        "Marco de Los Reyes"
    ],
    "wof:name":"Marco de Los Reyes",
    "wof:placetype":"locality"
},
  "geometry": {"coordinates":[-54.98519,-34.39185],"type":"Point"}
}