{
  "type": "Feature",
  "properties": {
    "gn:admin1_code":"04",
    "gn:asciiname":"Ismael Cortinas",
    "gn:country_code":"UY",
    "gn:dem":101,
    "gn:feature_class":"P",
    "gn:feature_code":"PPL",
    "gn:name":"Ismael Cortinas",
    "gn:population":0,
    "gn:timezone":"America/Montevideo",
    "iso:country":"UY",
    "name:cat_x_preferred":[
        "Ismael Cortinas"
    ],
    "name:deu_x_preferred":[
        "Ismael Cortinas"
    ],
    "name:fra_x_preferred":[
        "Ismael Cortinas"
    ],
    "name:hye_x_preferred":[
        "\u053b\u057d\u0574\u0561\u0575\u0565\u056c \u053f\u0578\u0580\u057f\u056b\u0576\u0561\u057d"
    ],
    "name:ita_x_preferred":[
        "Ismael Cortinas"
    ],
    "name:nor_x_preferred":[
        "Ismael Cortinas"
    ],
    "name:rus_x_preferred":[
        "\u0418\u0441\u043c\u0430\u044d\u043b\u044c-\u041a\u043e\u0440\u0442\u0438\u043d\u0430\u0441"
    ],
    "name:spa_x_preferred":[
        "Ismael Cortinas"
    ],
    "name:ukr_x_preferred":[
        "\u0406\u0441\u043c\u0430\u0435\u043b\u044c \u041a\u043e\u0440\u0442\u0456\u043d\u0430\u0441"
    ],
    "name:zho_x_preferred":[
        "\u4f0a\u65af\u6885\u723e\u79d1\u8482\u7d0d\u65af"
    ],
    "wof:name":"Ismael Cortinas",
    "wof:placetype":"locality"
},
  "geometry": {"coordinates":[-57.06667,-33.41667],"type":"Point"}
}