{
  "type": "Feature",
  "properties": {
    "gn:admin1_code":"04",
    "gn:asciiname":"Ismael Cortinas",
    "gn:country_code":"UY",
    "gn:dem":101,
    "gn:feature_class":"P",
    "gn:feature_code":"PPL",
    "gn:name":"Ismael Cortinas",
    "gn:population":0,
    "gn:timezone":"America/Montevideo",
    "iso:country":"UY",
    "wof:name":"Ismael Cortinas",
    "wof:placetype":"locality"
},
  "geometry": {"coordinates":[-57.06667,-33.41667],"type":"Point"}
}