{
  "type": "Feature",
  "properties": {
    "gn:admin1_code":"18",
    "gn:asciiname":"Quiebra Yugos",
    "gn:country_code":"UY",
    "gn:dem":151,
    "gn:feature_class":"P",
    "gn:feature_code":"PPL",
    "gn:name":"Quiebra Yugos",
    "gn:population":0,
    "gn:timezone":"America/Montevideo",
    "iso:country":"UY",
    "wof:name":"Quiebra Yugos",
    "wof:placetype":"locality"
},
  "geometry": {"coordinates":[-56.16667,-31.66667],"type":"Point"}
}