{
  "type": "Feature",
  "properties": {
    "gn:admin1_code":"08",
    "gn:asciiname":"Polanco Sur",
    "gn:country_code":"UY",
    "gn:dem":133,
    "gn:feature_class":"P",
    "gn:feature_code":"PPL",
    "gn:name":"Polanco Sur",
    "gn:population":0,
    "gn:timezone":"America/Montevideo",
    "iso:country":"UY",
    "name:spa_x_preferred":[
        "Polanco Sur"
    ],
    "wof:name":"Polanco Sur",
    "wof:placetype":"locality"
},
  "geometry": {"coordinates":[-55.16725,-33.89828],"type":"Point"}
}