{
  "type": "Feature",
  "properties": {
    "gn:admin1_code":"15",
    "gn:admin2_code":"05",
    "gn:asciiname":"Albisu",
    "gn:country_code":"UY",
    "gn:dem":60,
    "gn:feature_class":"P",
    "gn:feature_code":"PPL",
    "gn:name":"Albisu",
    "gn:population":0,
    "gn:timezone":"America/Montevideo",
    "iso:country":"UY",
    "wof:name":"Albisu",
    "wof:placetype":"locality"
},
  "geometry": {"coordinates":[-57.81469,-31.38411],"type":"Point"}
}