{
  "type": "Feature",
  "properties": {
    "gn:admin1_code":"15",
    "gn:admin2_code":"05",
    "gn:asciiname":"Albisu",
    "gn:country_code":"UY",
    "gn:dem":60,
    "gn:feature_class":"P",
    "gn:feature_code":"PPL",
    "gn:name":"Albisu",
    "gn:population":0,
    "gn:timezone":"America/Montevideo",
    "iso:country":"UY",
    "name:ceb_x_preferred":[
        "Albisu"
    ],
    "name:deu_x_preferred":[
        "Albisu"
    ],
    "name:fas_x_preferred":[
        "\u0627\u0644\u0628\u06cc\u0633\u0648"
    ],
    "name:fra_x_preferred":[
        "Albisu"
    ],
    "name:nor_x_preferred":[
        "Albisu"
    ],
    "name:spa_x_preferred":[
        "Albisu"
    ],
    "wof:name":"Albisu",
    "wof:placetype":"locality"
},
  "geometry": {"coordinates":[-57.81469,-31.38411],"type":"Point"}
}