{
  "type": "Feature",
  "properties": {
    "gn:admin1_code":"07",
    "gn:asciiname":"Mendoza",
    "gn:country_code":"UY",
    "gn:dem":54,
    "gn:feature_class":"P",
    "gn:feature_code":"PPL",
    "gn:name":"Mendoza",
    "gn:population":0,
    "gn:timezone":"America/Montevideo",
    "iso:country":"UY",
    "wof:name":"Mendoza",
    "wof:placetype":"locality"
},
  "geometry": {"coordinates":[-56.21441,-34.28211],"type":"Point"}
}