{
  "type": "Feature",
  "properties": {
    "gn:admin1_code":"07",
    "gn:asciiname":"Mendoza",
    "gn:country_code":"UY",
    "gn:dem":54,
    "gn:feature_class":"P",
    "gn:feature_code":"PPL",
    "gn:name":"Mendoza",
    "gn:population":0,
    "gn:timezone":"America/Montevideo",
    "iso:country":"UY",
    "name:ara_x_preferred":[
        "\u0645\u064a\u0646\u062f\u0648\u0632\u0627"
    ],
    "name:ben_x_preferred":[
        "\u09ae\u09c7\u09a8\u09cd\u09a1\u09cb\u09b8\u09be"
    ],
    "name:ell_x_preferred":[
        "\u039c\u03b5\u03bd\u03c4\u03cc\u03b6\u03b1"
    ],
    "name:heb_x_preferred":[
        "\u05de\u05e0\u05d2\u05e9"
    ],
    "name:hin_x_preferred":[
        "\u092e\u0947\u0902\u0921\u094b\u091c\u093c\u093e"
    ],
    "name:hun_x_preferred":[
        "Mendoza"
    ],
    "name:ind_x_preferred":[
        "Mendoza"
    ],
    "name:ita_x_preferred":[
        "Mendoza"
    ],
    "name:kor_x_preferred":[
        "\uba58\ub3c4\uc790"
    ],
    "name:urd_x_preferred":[
        "\u0645\u06cc\u0646\u0688\u0648\u0632\u0627"
    ],
    "name:vie_x_preferred":[
        "S\u00f4ng Mendoza"
    ],
    "wof:name":"Mendoza",
    "wof:placetype":"locality"
},
  "geometry": {"coordinates":[-56.21441,-34.28211],"type":"Point"}
}