{
  "type": "Feature",
  "properties": {
    "gn:admin1_code":"18",
    "gn:asciiname":"La Pedrera",
    "gn:country_code":"UY",
    "gn:dem":149,
    "gn:feature_class":"P",
    "gn:feature_code":"PPL",
    "gn:name":"La Pedrera",
    "gn:population":0,
    "gn:timezone":"America/Montevideo",
    "iso:country":"UY",
    "name:spa_x_preferred":[
        "La Pedrera"
    ],
    "wof:name":"La Pedrera",
    "wof:placetype":"locality"
},
  "geometry": {"coordinates":[-56.01357,-31.7214],"type":"Point"}
}