{
  "type": "Feature",
  "properties": {
    "iso:country":"UY",
    "name:cat_x_preferred":[
        "Flor de Maro\u00f1as"
    ],
    "name:deu_x_preferred":[
        "Flor de Maro\u00f1as"
    ],
    "name:pol_x_preferred":[
        "Flor de Maro\u00f1as"
    ],
    "name:spa_x_colloquial":[
        "Balneario Flor de Maronas",
        "Balneario Flor de Maronyas",
        "Flor de Maronas",
        "Flor de Maronyas",
        "Pueblo Ituzaingo"
    ],
    "name:spa_x_preferred":[
        "Flor de Maro\u00f1as"
    ],
    "name:spa_x_variant":[
        "Balneario Flor de Maro\u00f1as",
        "Pueblo Ituzaing\u00f3"
    ],
    "qs:gn_adm0_cc":"UY",
    "qs:gn_fcode":"PPLX",
    "qs:gn_local":5038018,
    "qs:gn_namadm1":"10",
    "qs:gn_name":"Flor de Maro\u00f1as",
    "qs:local_max":9496,
    "qs:local_sum":30959,
    "qs:localhoods":17,
    "qs:name":"Flor de Maro\u00f1as",
    "qs:name_adm0":"Uruguay",
    "qs:name_adm1":"Montevideo",
    "qs:name_local":"Montevideo",
    "qs:photo_max":9,
    "qs:photo_sum":36,
    "qs:placetype":"Suburb",
    "qs:quad_count":11,
    "qs:woe_adm0":23424979,
    "qs:woe_adm1":2347649,
    "qs:woe_adm2":0,
    "qs:woe_lau":0,
    "qs:woe_local":468052,
    "qs:woe_ver":"7.10.0",
    "wd:wordcount":69,
    "wof:lang":[
        "spa"
    ],
    "wof:name":"Flor de Maro\u00f1as",
    "wof:placetype":"neighbourhood"
},
  "geometry": {"coordinates":[-56.120758,-34.841232],"type":"Point"}
}