{
  "type": "Feature",
  "properties": {
    "gn:admin1_code":"07",
    "gn:asciiname":"Chamizo",
    "gn:country_code":"UY",
    "gn:dem":71,
    "gn:feature_class":"P",
    "gn:feature_code":"PPL",
    "gn:name":"Chamizo",
    "gn:population":0,
    "gn:timezone":"America/Montevideo",
    "iso:country":"UY",
    "name:ceb_x_preferred":[
        "Chamizo"
    ],
    "name:deu_x_preferred":[
        "Chamizo"
    ],
    "name:fra_x_preferred":[
        "Chamizo"
    ],
    "name:hye_x_preferred":[
        "\u0549\u0561\u0574\u056b\u057d\u056f\u0578"
    ],
    "name:nor_x_preferred":[
        "Chamizo"
    ],
    "name:rus_x_preferred":[
        "\u0427\u0430\u043c\u0438\u0441\u043e"
    ],
    "name:spa_x_preferred":[
        "Chamizo"
    ],
    "wof:name":"Chamizo",
    "wof:placetype":"locality"
},
  "geometry": {"coordinates":[-55.91673,-34.24132],"type":"Point"}
}