{
  "type": "Feature",
  "properties": {
    "gn:admin1_code":"13",
    "gn:asciiname":"Tres Cerros",
    "gn:country_code":"UY",
    "gn:dem":186,
    "gn:feature_class":"P",
    "gn:feature_code":"PPL",
    "gn:name":"Tres Cerros",
    "gn:population":0,
    "gn:timezone":"America/Montevideo",
    "iso:country":"UY",
    "wof:name":"Tres Cerros",
    "wof:placetype":"locality"
},
  "geometry": {"coordinates":[-55.66667,-31.36667000000001],"type":"Point"}
}