{
  "type": "Feature",
  "properties": {
    "gn:admin1_code":"18",
    "gn:asciiname":"Poblado Rincon de Giloca",
    "gn:cc2":"UY",
    "gn:country_code":"UY",
    "gn:dem":122,
    "gn:feature_class":"P",
    "gn:feature_code":"PPL",
    "gn:name":"Poblado Rinc\u00f3n de Giloca",
    "gn:population":0,
    "gn:timezone":"America/Montevideo",
    "iso:country":"UY",
    "name:und_x_variant":[
        "Rinc\u00f3n de Giloca",
        "Poblado Rinc\u00f3n de Giloca"
    ],
    "wof:name":"Poblado Rincon de Giloca",
    "wof:placetype":"locality"
},
  "geometry": {"coordinates":[-55.76667,-31.83333],"type":"Point"}
}