{
  "type": "Feature",
  "properties": {
    "iso:country":"UY",
    "name:cat_x_preferred":[
        "El Pinar"
    ],
    "name:ceb_x_preferred":[
        "El Pinar"
    ],
    "name:deu_x_preferred":[
        "El Pinar"
    ],
    "name:eng_x_preferred":[
        "El Pinar"
    ],
    "name:epo_x_preferred":[
        "El Pinar"
    ],
    "name:fra_x_preferred":[
        "El Pinar"
    ],
    "name:hun_x_preferred":[
        "El Pinar"
    ],
    "name:hye_x_preferred":[
        "\u0537\u056c \u054a\u056b\u0576\u0561\u0580"
    ],
    "name:nld_x_preferred":[
        "El Pinar"
    ],
    "name:nob_x_preferred":[
        "El Pinar"
    ],
    "name:nor_x_preferred":[
        "El Pinar"
    ],
    "name:pol_x_preferred":[
        "El Pinar"
    ],
    "name:por_x_preferred":[
        "El Pinar"
    ],
    "name:rus_x_preferred":[
        "\u042d\u043b\u044c-\u041f\u0438\u043d\u0430\u0440"
    ],
    "name:spa_x_preferred":[
        "El Pinar"
    ],
    "name:swe_x_preferred":[
        "El Pinar"
    ],
    "qs:gn_pop":0,
    "qs:name":"El Pinar",
    "qs:name_adm0":"Uruguay",
    "qs:name_adm1":"Canelones",
    "qs:photos":225,
    "qs:photos_1k":46,
    "qs:photos_9k":1,
    "qs:photos_9r":4,
    "qs:photos_all":225,
    "qs:photos_sr":4,
    "qs:placetype":"Town",
    "qs:pop_sr":"0",
    "qs:woe_adm0":23424979,
    "wd:wordcount":131,
    "wof:name":"El Pinar",
    "wof:placetype":"locality"
},
  "geometry": {"coordinates":[-55.890541,-34.794492],"type":"Point"}
}