{
  "type": "Feature",
  "properties": {
    "gn:admin1_code":"04",
    "gn:admin2_code":"09",
    "gn:asciiname":"Santa Regina",
    "gn:country_code":"UY",
    "gn:dem":4,
    "gn:feature_class":"P",
    "gn:feature_code":"PPL",
    "gn:name":"Santa Regina",
    "gn:population":0,
    "gn:timezone":"America/Montevideo",
    "iso:country":"UY",
    "name:spa_x_preferred":[
        "Santa Regina"
    ],
    "wof:name":"Santa Regina",
    "wof:placetype":"locality"
},
  "geometry": {"coordinates":[-57.19264,-34.43732],"type":"Point"}
}