{
  "type": "Feature",
  "properties": {
    "gn:admin1_code":"16",
    "gn:admin2_code":"02",
    "gn:asciiname":"Radial Ruta Tres",
    "gn:country_code":"UY",
    "gn:dem":36,
    "gn:feature_class":"P",
    "gn:feature_code":"PPL",
    "gn:name":"Radial Ruta Tres",
    "gn:population":0,
    "gn:timezone":"America/Montevideo",
    "iso:country":"UY",
    "name:spa_x_preferred":[
        "Radial Ruta Tres"
    ],
    "wof:name":"Radial Ruta Tres",
    "wof:placetype":"locality"
},
  "geometry": {"coordinates":[-56.76036,-34.55076],"type":"Point"}
}