{
  "type": "Feature",
  "properties": {
    "gn:admin1_code":"01",
    "gn:admin2_code":"03",
    "gn:asciiname":"Local Feria Itacumbu",
    "gn:country_code":"UY",
    "gn:dem":96,
    "gn:feature_class":"P",
    "gn:feature_code":"PPL",
    "gn:name":"Local Feria Itacumb\u00fa",
    "gn:population":0,
    "gn:timezone":"America/Montevideo",
    "iso:country":"UY",
    "name:spa_x_preferred":[
        "Local Feria Itacumb\u00fa"
    ],
    "wof:name":"Local Feria Itacumbu",
    "wof:placetype":"locality"
},
  "geometry": {"coordinates":[-57.41529,-30.4848],"type":"Point"}
}