{
  "type": "Feature",
  "properties": {
    "iso:country":"UY",
    "qs:gn_pop":0,
    "qs:name":"Bello Horizonte",
    "qs:name_adm0":"Uruguay",
    "qs:name_adm1":"Canelones",
    "qs:photos":27,
    "qs:photos_1k":5,
    "qs:photos_9k":1,
    "qs:photos_9r":2,
    "qs:photos_all":27,
    "qs:photos_sr":2,
    "qs:placetype":"Town",
    "qs:pop_sr":"0",
    "qs:woe_adm0":23424979,
    "wof:name":"Bello Horizonte",
    "wof:placetype":"locality"
},
  "geometry": {"coordinates":[-55.633907,-34.771123],"type":"Point"}
}