{
  "type": "Feature",
  "properties": {
    "gn:admin1_code":"15",
    "gn:admin2_code":"02",
    "gn:asciiname":"El Espinillar",
    "gn:country_code":"UY",
    "gn:dem":45,
    "gn:feature_class":"P",
    "gn:feature_code":"PPL",
    "gn:name":"El Espinillar",
    "gn:population":0,
    "gn:timezone":"America/Argentina/Cordoba",
    "iso:country":"UY",
    "name:spa_x_preferred":[
        "El Espinillar"
    ],
    "wof:name":"El Espinillar",
    "wof:placetype":"locality"
},
  "geometry": {"coordinates":[-57.84498000000001,-30.95617],"type":"Point"}
}