{
  "type": "Feature",
  "properties": {
    "gn:admin1_code":"03",
    "gn:asciiname":"La Pedrera",
    "gn:country_code":"UY",
    "gn:dem":122,
    "gn:feature_class":"P",
    "gn:feature_code":"PPL",
    "gn:name":"La Pedrera",
    "gn:population":0,
    "gn:timezone":"America/Montevideo",
    "iso:country":"UY",
    "wof:name":"La Pedrera",
    "wof:placetype":"locality"
},
  "geometry": {"coordinates":[-54.13333000000001,-32.35],"type":"Point"}
}