{
  "type": "Feature",
  "properties": {
    "gn:admin1_code":"02",
    "gn:asciiname":"La Sierra",
    "gn:country_code":"UY",
    "gn:dem":32,
    "gn:feature_class":"P",
    "gn:feature_code":"PPL",
    "gn:name":"La Sierra",
    "gn:population":0,
    "gn:timezone":"America/Montevideo",
    "iso:country":"UY",
    "wof:name":"La Sierra",
    "wof:placetype":"locality"
},
  "geometry": {"coordinates":[-55.40015,-34.74734],"type":"Point"}
}