{
  "type": "Feature",
  "properties": {
    "gn:admin1_code":"07",
    "gn:asciiname":"Juncal",
    "gn:country_code":"UY",
    "gn:dem":68,
    "gn:feature_class":"P",
    "gn:feature_code":"PPL",
    "gn:name":"Juncal",
    "gn:population":0,
    "gn:timezone":"America/Montevideo",
    "iso:country":"UY",
    "name:ceb_x_preferred":[
        "Juncal"
    ],
    "name:fra_x_preferred":[
        "Juncal"
    ],
    "name:kaz_x_preferred":[
        "\u0416\u0443\u043d\u043a\u0430\u043b"
    ],
    "name:msa_x_preferred":[
        "Juncal"
    ],
    "name:rus_x_preferred":[
        "\u0416\u0443\u043d\u043a\u0430\u043b"
    ],
    "name:spa_x_preferred":[
        "Juncal"
    ],
    "wof:name":"Juncal",
    "wof:placetype":"locality"
},
  "geometry": {"coordinates":[-56.18512,-34.09708],"type":"Point"}
}