{
  "type": "Feature",
  "properties": {
    "gn:country":"UY",
    "gn:fcode":"PPL",
    "gn:population":1202,
    "iso:country":"UY",
    "name:cat_x_preferred":[
        "Dieciocho de Julio"
    ],
    "name:deu_x_preferred":[
        "18 de Julio"
    ],
    "name:eng_x_preferred":[
        "Dieciocho de Julio"
    ],
    "name:fra_x_preferred":[
        "Dieciocho de Julio"
    ],
    "name:nld_x_preferred":[
        "Dieciocho de Julio"
    ],
    "name:nob_x_preferred":[
        "Dieciocho de Julio"
    ],
    "name:rus_x_preferred":[
        "18 \u0438\u044e\u043b\u044f"
    ],
    "name:spa_x_preferred":[
        "18 de Julio"
    ],
    "qs_pg:aaroncc":"UY",
    "qs_pg:gn_country":"UY",
    "qs_pg:gn_fcode":"PPL",
    "qs_pg:gn_pop":1202,
    "qs_pg:name":"Dieciocho de Julio",
    "qs_pg:photos_9r":0,
    "qs_pg:photos_sr":0,
    "qs_pg:pop_sr":3,
    "qs_pg:qs_pg_placetype":"locality",
    "wof:name":"Dieciocho de Julio",
    "wof:placetype":"locality",
    "wof:population":1202
},
  "geometry": {"coordinates":[-53.55,-33.68333],"type":"Point"}
}