{
  "type": "Feature",
  "properties": {
    "iso:country":"UY",
    "name:ara_x_preferred":[
        "\u0633\u0627\u0646 \u0644\u0648\u064a\u0633"
    ],
    "name:ben_x_preferred":[
        "\u09b8\u09be\u09a8 \u09b2\u09c1\u0987"
    ],
    "name:cat_x_preferred":[
        "San Luis"
    ],
    "name:deu_x_preferred":[
        "San Luis"
    ],
    "name:ell_x_preferred":[
        "\u03a3\u03b1\u03bd \u039b\u03bf\u03c5\u03cc\u03c2"
    ],
    "name:eng_x_preferred":[
        "San Luis"
    ],
    "name:fas_x_preferred":[
        "\u0633\u0646 \u0644\u0648\u0626\u06cc\u0632"
    ],
    "name:fra_x_preferred":[
        "San Luis"
    ],
    "name:heb_x_preferred":[
        "\u05e1\u05df \u05dc\u05d5\u05d0\u05d9\u05e1"
    ],
    "name:hin_x_preferred":[
        "\u0938\u0948\u0928 \u0932\u0941\u0908"
    ],
    "name:hun_x_preferred":[
        "San Luis"
    ],
    "name:ind_x_preferred":[
        "San Luis"
    ],
    "name:jpn_x_preferred":[
        "\u30b5\u30f3\u30eb\u30a4\u30b9"
    ],
    "name:kor_x_preferred":[
        "\uc0b0 \ub8e8\uc774\uc2a4"
    ],
    "name:nld_x_preferred":[
        "San Luis"
    ],
    "name:nob_x_preferred":[
        "San Luis"
    ],
    "name:rus_x_preferred":[
        "\u0421\u0430\u043d-\u041b\u0443\u0438\u0441"
    ],
    "name:spa_x_preferred":[
        "San Luis"
    ],
    "name:tur_x_preferred":[
        "San Luis"
    ],
    "name:ukr_x_preferred":[
        "\u0421\u0430\u043d-\u041b\u0443\u0457\u0441"
    ],
    "name:urd_x_preferred":[
        "\u0633\u0627\u0646 \u0644\u0648\u0626\u0633"
    ],
    "name:vie_x_preferred":[
        "San Luis"
    ],
    "qs:gn_pop":0,
    "qs:name":"San Luis",
    "qs:name_adm0":"Uruguay",
    "qs:name_adm1":"Canelones",
    "qs:photos":76,
    "qs:photos_1k":15,
    "qs:photos_9k":1,
    "qs:photos_9r":3,
    "qs:photos_all":76,
    "qs:photos_sr":3,
    "qs:placetype":"Town",
    "qs:pop_sr":"0",
    "qs:woe_adm0":23424979,
    "wof:name":"San Luis",
    "wof:placetype":"locality"
},
  "geometry": {"coordinates":[-55.61172,-34.77041],"type":"Point"}
}