{
  "type": "Feature",
  "properties": {
    "iso:country":"UY",
    "name:cat_x_preferred":[
        "San Luis"
    ],
    "name:deu_x_preferred":[
        "San Luis"
    ],
    "name:eng_x_preferred":[
        "San Luis"
    ],
    "name:fra_x_preferred":[
        "San Luis"
    ],
    "name:nld_x_preferred":[
        "San Luis"
    ],
    "name:nob_x_preferred":[
        "San Luis"
    ],
    "name:spa_x_preferred":[
        "San Luis"
    ],
    "qs:gn_pop":0,
    "qs:name":"San Luis",
    "qs:name_adm0":"Uruguay",
    "qs:name_adm1":"Canelones",
    "qs:photos":76,
    "qs:photos_1k":15,
    "qs:photos_9k":1,
    "qs:photos_9r":3,
    "qs:photos_all":76,
    "qs:photos_sr":3,
    "qs:placetype":"Town",
    "qs:pop_sr":"0",
    "qs:woe_adm0":23424979,
    "wof:name":"San Luis",
    "wof:placetype":"locality"
},
  "geometry": {"coordinates":[-55.61172,-34.77041],"type":"Point"}
}