{
  "type": "Feature",
  "properties": {
    "gn:admin1_code":"15",
    "gn:admin2_code":"06",
    "gn:asciiname":"Valentin Grande",
    "gn:country_code":"UY",
    "gn:dem":77,
    "gn:feature_class":"P",
    "gn:feature_code":"PPL",
    "gn:name":"Valent\u00edn Grande",
    "gn:population":0,
    "gn:timezone":"America/Montevideo",
    "iso:country":"UY",
    "name:und_x_variant":[
        "Poblacion Valentin",
        "Valent\u00edn Grande",
        "Valent\u00edn"
    ],
    "wof:name":"Valentin Grande",
    "wof:placetype":"locality"
},
  "geometry": {"coordinates":[-57.15684,-31.27347],"type":"Point"}
}