{
  "type": "Feature",
  "properties": {
    "gn:admin1_code":"19",
    "gn:asciiname":"Julio Maria Sanz",
    "gn:country_code":"UY",
    "gn:dem":57,
    "gn:feature_class":"P",
    "gn:feature_code":"PPL",
    "gn:name":"Julio Mar\u00eda Sanz",
    "gn:population":0,
    "gn:timezone":"America/Montevideo",
    "iso:country":"UY",
    "wof:name":"Julio Maria Sanz",
    "wof:placetype":"locality"
},
  "geometry": {"coordinates":[-54.15,-33.15],"type":"Point"}
}