{
  "type": "Feature",
  "properties": {
    "gn:admin1_code":"15",
    "gn:admin2_code":"03",
    "gn:asciiname":"Paso Nuevo del Arapey",
    "gn:country_code":"UY",
    "gn:dem":184,
    "gn:feature_class":"P",
    "gn:feature_code":"PPL",
    "gn:name":"Paso Nuevo del Arapey",
    "gn:population":0,
    "gn:timezone":"America/Montevideo",
    "iso:country":"UY",
    "name:spa_x_preferred":[
        "Paso Nuevo del Arapey"
    ],
    "wof:name":"Paso Nuevo del Arapey",
    "wof:placetype":"locality"
},
  "geometry": {"coordinates":[-56.66341,-31.12686],"type":"Point"}
}