{
  "type": "Feature",
  "properties": {
    "gn:country":"UY",
    "gn:fcode":"PPL",
    "gn:population":1036,
    "iso:country":"UY",
    "name:cat_x_preferred":[
        "Carlos Reyles"
    ],
    "name:ceb_x_preferred":[
        "Molles"
    ],
    "name:deu_x_preferred":[
        "Carlos Reyles"
    ],
    "name:eng_x_preferred":[
        "Carlos Reyles"
    ],
    "name:fra_x_preferred":[
        "Carlos Reyles"
    ],
    "name:hye_x_preferred":[
        "\u053f\u0561\u0580\u056c\u0578\u057d \u054c\u0565\u0575\u056c\u0565\u057d"
    ],
    "name:nld_x_preferred":[
        "Carlos Reyles"
    ],
    "name:nob_x_preferred":[
        "Carlos Reyles"
    ],
    "name:rus_x_preferred":[
        "\u041a\u0430\u0440\u043b\u043e\u0441-\u0420\u0435\u0439\u043b\u0435\u0441"
    ],
    "name:spa_x_preferred":[
        "Carlos Reyles"
    ],
    "qs:name":"Carlos Reyles",
    "qs:photos_9r":0,
    "qs:photos_sr":0,
    "qs:pop_sr":"3",
    "wd:wordcount":188,
    "wof:name":"Carlos Reyles",
    "wof:placetype":"locality",
    "wof:population":1036
},
  "geometry": {"coordinates":[-56.48333,-33.01667],"type":"Point"}
}